[
  {
    "car": 0,
    "year": 2005,
    "firm_id": 3,
    "firm_name": "HONDA",
    "division": "Acura",
    "model": "MDX",
    "hybrid": 0,
    "segm1": 39,
    "Quantity": 57948,
    "Price": 36970,
    "wheel_base": 106.3,
    "length": 188.7,
    "width": 77,
    "weight": 4451,
    "disp": 3.5,
    "hp": 265,
    "mpg_city": 17,
    "mpg_highway": 23,
    "": "",
    "__1": ""
  },
  {
    "car": 0,
    "year": 2005,
    "firm_id": 8,
    "firm_name": "BMW",
    "division": "BMW",
    "model": "X3",
    "hybrid": 0,
    "segm1": 39,
    "Quantity": 30769,
    "Price": 30995,
    "wheel_base": 110.1,
    "length": 179.7,
    "width": 73,
    "weight": 4001,
    "disp": 2.5,
    "hp": 184,
    "mpg_city": 17,
    "mpg_highway": 24,
    "": "",
    "__1": ""
  },
  {
    "car": 0,
    "year": 2005,
    "firm_id": 8,
    "firm_name": "BMW",
    "division": "BMW",
    "model": "X5",
    "hybrid": 0,
    "segm1": 39,
    "Quantity": 37598,
    "Price": 42395,
    "wheel_base": 111,
    "length": 183.7,
    "width": 73.7,
    "weight": 4652,
    "disp": 3,
    "hp": 225,
    "mpg_city": 15,
    "mpg_highway": 21,
    "": "",
    "__1": ""
  },
  {
    "car": 0,
    "year": 2005,
    "firm_id": 19,
    "firm_name": "GM",
    "division": "Buick",
    "model": "Rainier",
    "hybrid": 0,
    "segm1": 34,
    "Quantity": 15271,
    "Price": 35765,
    "wheel_base": 113,
    "length": 193.4,
    "width": 75.4,
    "weight": 4442,
    "disp": 4.2,
    "hp": 275,
    "mpg_city": 16,
    "mpg_highway": 21,
    "": "",
    "__1": ""
  },
  {
    "car": 0,
    "year": 2005,
    "firm_id": 19,
    "firm_name": "GM",
    "division": "Buick",
    "model": "Rendezvous",
    "hybrid": 0,
    "segm1": 38,
    "Quantity": 60589,
    "Price": 27270,
    "wheel_base": 112.2,
    "length": 186.5,
    "width": 73.6,
    "weight": 4024,
    "disp": 3.4,
    "hp": 185,
    "mpg_city": 19,
    "mpg_highway": 26,
    "": "",
    "__1": ""
  },
  {
    "car": 0,
    "year": 2005,
    "firm_id": 19,
    "firm_name": "GM",
    "division": "Cadillac",
    "model": "Escalade",
    "hybrid": 0,
    "segm1": 34,
    "Quantity": 29876,
    "Price": 53715,
    "wheel_base": 116,
    "length": 198.9,
    "width": 78.9,
    "weight": 5367,
    "disp": 5.3,
    "hp": 295,
    "mpg_city": 14,
    "mpg_highway": 18,
    "": "",
    "__1": ""
  },
  {
    "car": 0,
    "year": 2005,
    "firm_id": 19,
    "firm_name": "GM",
    "division": "Cadillac",
    "model": "Escalade EXT",
    "hybrid": 0,
    "segm1": 35,
    "Quantity": 21268,
    "Price": 53895,
    "wheel_base": 130,
    "length": 221,
    "width": 79.5,
    "weight": 5886,
    "disp": 6,
    "hp": 345,
    "mpg_city": 13,
    "mpg_highway": 17,
    "": "",
    "__1": ""
  },
  {
    "car": 0,
    "year": 2005,
    "firm_id": 19,
    "firm_name": "GM",
    "division": "Cadillac",
    "model": "SRX",
    "hybrid": 0,
    "segm1": 39,
    "Quantity": 22999,
    "Price": 39035,
    "wheel_base": 116,
    "length": 195,
    "width": 72.6,
    "weight": 4229,
    "disp": 3.6,
    "hp": 255,
    "mpg_city": 16,
    "mpg_highway": 23,
    "": "",
    "__1": ""
  },
  {
    "car": 0,
    "year": 2005,
    "firm_id": 19,
    "firm_name": "GM",
    "division": "Chevrolet",
    "model": "Astro",
    "hybrid": 0,
    "segm1": 21,
    "Quantity": 19215,
    "Price": 25040,
    "wheel_base": 111.2,
    "length": 189.8,
    "width": 77.5,
    "weight": 4321,
    "disp": 4.3,
    "hp": 190,
    "mpg_city": 16,
    "mpg_highway": 20,
    "": "",
    "__1": ""
  },
  {
    "car": 0,
    "year": 2005,
    "firm_id": 19,
    "firm_name": "GM",
    "division": "Chevrolet",
    "model": "Avalanche",
    "hybrid": 0,
    "segm1": 35,
    "Quantity": 63186,
    "Price": 34170,
    "wheel_base": 130,
    "length": 221.7,
    "width": 79.8,
    "weight": 5437,
    "disp": 5.3,
    "hp": 295,
    "mpg_city": 14,
    "mpg_highway": 18,
    "": "",
    "__1": ""
  },
  {
    "car": 0,
    "year": 2005,
    "firm_id": 19,
    "firm_name": "GM",
    "division": "Chevrolet",
    "model": "Blazer",
    "hybrid": 0,
    "segm1": 32,
    "Quantity": 4936,
    "Price": 21850,
    "wheel_base": 100.5,
    "length": 176.8,
    "width": 67.8,
    "weight": 3591,
    "disp": 4.3,
    "hp": 190,
    "mpg_city": 15,
    "mpg_highway": 21,
    "": "",
    "__1": ""
  },
  {
    "car": 0,
    "year": 2005,
    "firm_id": 19,
    "firm_name": "GM",
    "division": "Chevrolet",
    "model": "Colorado",
    "hybrid": 0,
    "segm1": 41,
    "Quantity": 128359,
    "Price": 16430,
    "wheel_base": 111.3,
    "length": 192.8,
    "width": 67.6,
    "weight": 3117,
    "disp": 2.8,
    "hp": 175,
    "mpg_city": 21,
    "mpg_highway": 27,
    "": "",
    "__1": ""
  },
  {
    "car": 0,
    "year": 2005,
    "firm_id": 19,
    "firm_name": "GM",
    "division": "Chevrolet",
    "model": "Equinox",
    "hybrid": 0,
    "segm1": 38,
    "Quantity": 130542,
    "Price": 21660,
    "wheel_base": 112.5,
    "length": 188.8,
    "width": 71.4,
    "weight": 3660,
    "disp": 3.4,
    "hp": 185,
    "mpg_city": 19,
    "mpg_highway": 25,
    "": "",
    "__1": ""
  },
  {
    "car": 0,
    "year": 2005,
    "firm_id": 19,
    "firm_name": "GM",
    "division": "Chevrolet",
    "model": "Express/VAN",
    "hybrid": 0,
    "segm1": 22,
    "Quantity": 127585,
    "Price": 23575,
    "wheel_base": 135,
    "length": 224.1,
    "width": 79.4,
    "weight": 4845,
    "disp": 4.3,
    "hp": 195,
    "mpg_city": 14,
    "mpg_highway": 18,
    "": "",
    "__1": ""
  },
  {
    "car": 0,
    "year": 2005,
    "firm_id": 19,
    "firm_name": "GM",
    "division": "Chevrolet",
    "model": "Silverado C/K",
    "hybrid": 0,
    "segm1": 42,
    "Quantity": 705980,
    "Price": 19620,
    "wheel_base": 119,
    "length": 203.3,
    "width": 78.5,
    "weight": 4142,
    "disp": 4.3,
    "hp": 195,
    "mpg_city": 17,
    "mpg_highway": 23,
    "": "",
    "__1": ""
  },
  {
    "car": 0,
    "year": 2005,
    "firm_id": 19,
    "firm_name": "GM",
    "division": "Chevrolet",
    "model": "SSR",
    "hybrid": 0,
    "segm1": 41,
    "Quantity": 8107,
    "Price": 43055,
    "wheel_base": 116,
    "length": 191.4,
    "width": 78.6,
    "weight": 4760,
    "disp": 5.3,
    "hp": 300,
    "mpg_city": 17,
    "mpg_highway": 23,
    "": "",
    "__1": ""
  },
  {
    "car": 0,
    "year": 2005,
    "firm_id": 19,
    "firm_name": "GM",
    "division": "Chevrolet",
    "model": "Suburban",
    "hybrid": 0,
    "segm1": 33,
    "Quantity": 87011,
    "Price": 38875,
    "wheel_base": 130,
    "length": 219.3,
    "width": 78.9,
    "weight": 4947,
    "disp": 5.3,
    "hp": 285,
    "mpg_city": 14,
    "mpg_highway": 19,
    "": "",
    "__1": ""
  },
  {
    "car": 0,
    "year": 2005,
    "firm_id": 19,
    "firm_name": "GM",
    "division": "Chevrolet",
    "model": "Tahoe",
    "hybrid": 0,
    "segm1": 33,
    "Quantity": 152305,
    "Price": 36025,
    "wheel_base": 116,
    "length": 196.9,
    "width": 78.9,
    "weight": 4828,
    "disp": 4.8,
    "hp": 285,
    "mpg_city": 14,
    "mpg_highway": 18,
    "": "",
    "__1": ""
  },
  {
    "car": 0,
    "year": 2005,
    "firm_id": 19,
    "firm_name": "GM",
    "division": "Chevrolet",
    "model": "Trailblazer",
    "hybrid": 0,
    "segm1": 32,
    "Quantity": 244150,
    "Price": 28405,
    "wheel_base": 113,
    "length": 191.8,
    "width": 74.6,
    "weight": 4417,
    "disp": 4.2,
    "hp": 275,
    "mpg_city": 16,
    "mpg_highway": 21,
    "": "",
    "__1": ""
  },
  {
    "car": 0,
    "year": 2005,
    "firm_id": 19,
    "firm_name": "GM",
    "division": "Chevrolet",
    "model": "Venture",
    "hybrid": 0,
    "segm1": 21,
    "Quantity": 7029,
    "Price": 24080,
    "wheel_base": 211,
    "length": 200.9,
    "width": 72,
    "weight": 3838,
    "disp": 3.4,
    "hp": 185,
    "mpg_city": 19,
    "mpg_highway": 26,
    "": "",
    "__1": ""
  },
  {
    "car": 0,
    "year": 2005,
    "firm_id": 16,
    "firm_name": "CHRYSLER",
    "division": "Chrysler",
    "model": "Pacifica",
    "hybrid": 0,
    "segm1": 39,
    "Quantity": 85557,
    "Price": 27975,
    "wheel_base": 116.3,
    "length": 198.9,
    "width": 79.3,
    "weight": 4560,
    "disp": 3.5,
    "hp": 250,
    "mpg_city": 17,
    "mpg_highway": 22,
    "": "",
    "__1": ""
  },
  {
    "car": 0,
    "year": 2005,
    "firm_id": 16,
    "firm_name": "CHRYSLER",
    "division": "Chrysler",
    "model": "Town & country",
    "hybrid": 0,
    "segm1": 21,
    "Quantity": 180759,
    "Price": 25640,
    "wheel_base": 119.3,
    "length": 200.6,
    "width": 78.6,
    "weight": 4239,
    "disp": 3.3,
    "hp": 180,
    "mpg_city": 19,
    "mpg_highway": 26,
    "": "",
    "__1": ""
  },
  {
    "car": 0,
    "year": 2005,
    "firm_id": 16,
    "firm_name": "CHRYSLER",
    "division": "Dodge",
    "model": "Caravan",
    "hybrid": 0,
    "segm1": 21,
    "Quantity": 24944,
    "Price": 18995,
    "wheel_base": 113.3,
    "length": 189.3,
    "width": 78.6,
    "weight": 3817,
    "disp": 2.4,
    "hp": 150,
    "mpg_city": 20,
    "mpg_highway": 26,
    "": "",
    "__1": ""
  },
  {
    "car": 0,
    "year": 2005,
    "firm_id": 16,
    "firm_name": "CHRYSLER",
    "division": "Dodge",
    "model": "Dakota",
    "hybrid": 0,
    "segm1": 41,
    "Quantity": 104051,
    "Price": 20019,
    "wheel_base": 131,
    "length": 218.8,
    "width": 71.6,
    "weight": 4306,
    "disp": 3.7,
    "hp": 210,
    "mpg_city": 16,
    "mpg_highway": 22,
    "": "",
    "__1": ""
  },
  {
    "car": 0,
    "year": 2005,
    "firm_id": 16,
    "firm_name": "CHRYSLER",
    "division": "Dodge",
    "model": "Durango",
    "hybrid": 0,
    "segm1": 32,
    "Quantity": 115439,
    "Price": 27380,
    "wheel_base": 119.2,
    "length": 200.8,
    "width": 76,
    "weight": 4671,
    "disp": 3.7,
    "hp": 210,
    "mpg_city": 16,
    "mpg_highway": 21,
    "": "",
    "__1": ""
  },
  {
    "car": 0,
    "year": 2005,
    "firm_id": 16,
    "firm_name": "CHRYSLER",
    "division": "Dodge",
    "model": "Magnum",
    "hybrid": 0,
    "segm1": 38,
    "Quantity": 52487,
    "Price": 22495,
    "wheel_base": 120,
    "length": 197.7,
    "width": 74.1,
    "weight": 3847,
    "disp": 2.7,
    "hp": 190,
    "mpg_city": 21,
    "mpg_highway": 28,
    "": "",
    "__1": ""
  },
  {
    "car": 0,
    "year": 2005,
    "firm_id": 16,
    "firm_name": "CHRYSLER",
    "division": "Dodge",
    "model": "Ram",
    "hybrid": 0,
    "segm1": 42,
    "Quantity": 400543,
    "Price": 25415,
    "wheel_base": 140.5,
    "length": 229.7,
    "width": 79.6,
    "weight": 5453,
    "disp": 5.7,
    "hp": 345,
    "mpg_city": 12,
    "mpg_highway": 16,
    "": "",
    "__1": ""
  },
  {
    "car": 0,
    "year": 2005,
    "firm_id": 18,
    "firm_name": "FORD",
    "division": "Ford",
    "model": "Econoline van/wagon",
    "hybrid": 0,
    "segm1": 22,
    "Quantity": 179543,
    "Price": 23330,
    "wheel_base": 138,
    "length": 211.9,
    "width": 79.3,
    "weight": 4773,
    "disp": 4.6,
    "hp": 225,
    "mpg_city": 15,
    "mpg_highway": 19,
    "": "",
    "__1": ""
  },
  {
    "car": 0,
    "year": 2005,
    "firm_id": 18,
    "firm_name": "FORD",
    "division": "Ford",
    "model": "Escape",
    "hybrid": 0,
    "segm1": 38,
    "Quantity": 165122,
    "Price": 19995,
    "wheel_base": 103.1,
    "length": 174.9,
    "width": 70.1,
    "weight": 3176,
    "disp": 2.3,
    "hp": 153,
    "mpg_city": 23,
    "mpg_highway": 27,
    "": "",
    "__1": ""
  },
  {
    "car": 0,
    "year": 2005,
    "firm_id": 18,
    "firm_name": "FORD",
    "division": "Ford",
    "model": "Excursion",
    "hybrid": 0,
    "segm1": 33,
    "Quantity": 16283,
    "Price": 37810,
    "wheel_base": 137.1,
    "length": 226.4,
    "width": 79.9,
    "weight": 6680,
    "disp": 5.4,
    "hp": 255,
    "mpg_city": 12,
    "mpg_highway": 15,
    "": "",
    "__1": ""
  },
  {
    "car": 0,
    "year": 2005,
    "firm_id": 18,
    "firm_name": "FORD",
    "division": "Ford",
    "model": "Expedition",
    "hybrid": 0,
    "segm1": 33,
    "Quantity": 114137,
    "Price": 33365,
    "wheel_base": 119.1,
    "length": 205.8,
    "width": 78.6,
    "weight": 5352,
    "disp": 5.4,
    "hp": 300,
    "mpg_city": 13,
    "mpg_highway": 17,
    "": "",
    "__1": ""
  },
  {
    "car": 0,
    "year": 2005,
    "firm_id": 18,
    "firm_name": "FORD",
    "division": "Ford",
    "model": "Explorer",
    "hybrid": 0,
    "segm1": 32,
    "Quantity": 239788,
    "Price": 31020,
    "wheel_base": 113.7,
    "length": 189.5,
    "width": 72.1,
    "weight": 4309,
    "disp": 4.6,
    "hp": 239,
    "mpg_city": 15,
    "mpg_highway": 20,
    "": "",
    "__1": ""
  },
  {
    "car": 0,
    "year": 2005,
    "firm_id": 18,
    "firm_name": "FORD",
    "division": "Ford",
    "model": "Freestar",
    "hybrid": 0,
    "segm1": 21,
    "Quantity": 77585,
    "Price": 22295,
    "wheel_base": 120.8,
    "length": 201,
    "width": 76.6,
    "weight": 4150,
    "disp": 3.9,
    "hp": 193,
    "mpg_city": 18,
    "mpg_highway": 23,
    "": "",
    "__1": ""
  },
  {
    "car": 0,
    "year": 2005,
    "firm_id": 18,
    "firm_name": "FORD",
    "division": "Ford",
    "model": "F series",
    "hybrid": 0,
    "segm1": 42,
    "Quantity": 901463,
    "Price": 23365,
    "wheel_base": 137,
    "length": 226.6,
    "width": 76.5,
    "weight": 5648,
    "disp": 5.4,
    "hp": 300,
    "mpg_city": 14,
    "mpg_highway": 17,
    "": "",
    "__1": ""
  },
  {
    "car": 0,
    "year": 2005,
    "firm_id": 18,
    "firm_name": "FORD",
    "division": "Ford",
    "model": "Ranger",
    "hybrid": 0,
    "segm1": 41,
    "Quantity": 120958,
    "Price": 14985,
    "wheel_base": 111.5,
    "length": 188.5,
    "width": 66.2,
    "weight": 3010,
    "disp": 2.3,
    "hp": 148,
    "mpg_city": 24,
    "mpg_highway": 29,
    "": "",
    "__1": ""
  },
  {
    "car": 0,
    "year": 2005,
    "firm_id": 18,
    "firm_name": "FORD",
    "division": "Ford",
    "model": "Freestyle",
    "hybrid": 0,
    "segm1": 38,
    "Quantity": 76739,
    "Price": 25595,
    "wheel_base": 112.9,
    "length": 199.8,
    "width": 73,
    "weight": 3959,
    "disp": 3,
    "hp": 203,
    "mpg_city": 20,
    "mpg_highway": 27,
    "": "",
    "__1": ""
  },
  {
    "car": 0,
    "year": 2005,
    "firm_id": 19,
    "firm_name": "GM",
    "division": "GMC",
    "model": "Canyon",
    "hybrid": 0,
    "segm1": 41,
    "Quantity": 34845,
    "Price": 16760,
    "wheel_base": 111.3,
    "length": 192.4,
    "width": 67.6,
    "weight": 3375,
    "disp": 2.8,
    "hp": 175,
    "mpg_city": 21,
    "mpg_highway": 27,
    "": "",
    "__1": ""
  },
  {
    "car": 0,
    "year": 2005,
    "firm_id": 19,
    "firm_name": "GM",
    "division": "GMC",
    "model": "Envoy",
    "hybrid": 0,
    "segm1": 32,
    "Quantity": 107862,
    "Price": 30435,
    "wheel_base": 113,
    "length": 191.6,
    "width": 74.7,
    "weight": 4425,
    "disp": 4.2,
    "hp": 275,
    "mpg_city": 16,
    "mpg_highway": 21,
    "": "",
    "__1": ""
  },
  {
    "car": 0,
    "year": 2005,
    "firm_id": 19,
    "firm_name": "GM",
    "division": "GMC",
    "model": "Safari",
    "hybrid": 0,
    "segm1": 21,
    "Quantity": 3436,
    "Price": 25040,
    "wheel_base": 111.2,
    "length": 189.8,
    "width": 77.5,
    "weight": 4309,
    "disp": 4.3,
    "hp": 190,
    "mpg_city": 16,
    "mpg_highway": 20,
    "": "",
    "__1": ""
  },
  {
    "car": 0,
    "year": 2005,
    "firm_id": 19,
    "firm_name": "GM",
    "division": "GMC",
    "model": "Savana",
    "hybrid": 0,
    "segm1": 22,
    "Quantity": 34765,
    "Price": 26305,
    "wheel_base": 135,
    "length": 224.1,
    "width": 79.4,
    "weight": 5258,
    "disp": 4.3,
    "hp": 195,
    "mpg_city": 14,
    "mpg_highway": 18,
    "": "",
    "__1": ""
  },
  {
    "car": 0,
    "year": 2005,
    "firm_id": 19,
    "firm_name": "GM",
    "division": "GMC",
    "model": "Sierra",
    "hybrid": 0,
    "segm1": 42,
    "Quantity": 229488,
    "Price": 19620,
    "wheel_base": 119,
    "length": 205.7,
    "width": 78.5,
    "weight": 4225,
    "disp": 4.3,
    "hp": 195,
    "mpg_city": 17,
    "mpg_highway": 23,
    "": "",
    "__1": ""
  },
  {
    "car": 0,
    "year": 2005,
    "firm_id": 19,
    "firm_name": "GM",
    "division": "GMC",
    "model": "Suburban Yukon XLon xL",
    "hybrid": 0,
    "segm1": 33,
    "Quantity": 53652,
    "Price": 39535,
    "wheel_base": 130,
    "length": 219.3,
    "width": 78.9,
    "weight": 5268,
    "disp": 5.3,
    "hp": 295,
    "mpg_city": 14,
    "mpg_highway": 19,
    "": "",
    "__1": ""
  },
  {
    "car": 0,
    "year": 2005,
    "firm_id": 19,
    "firm_name": "GM",
    "division": "GMC",
    "model": "Yukon Denali",
    "hybrid": 0,
    "segm1": 33,
    "Quantity": 73458,
    "Price": 36485,
    "wheel_base": 116,
    "length": 198.8,
    "width": 78.8,
    "weight": 4975,
    "disp": 4.8,
    "hp": 285,
    "mpg_city": 16,
    "mpg_highway": 20,
    "": "",
    "__1": ""
  },
  {
    "car": 0,
    "year": 2005,
    "firm_id": 3,
    "firm_name": "HONDA",
    "division": "Honda",
    "model": "CR-V",
    "hybrid": 0,
    "segm1": 38,
    "Quantity": 150219,
    "Price": 20510,
    "wheel_base": 103.3,
    "length": 181,
    "width": 70.2,
    "weight": 3318,
    "disp": 2.4,
    "hp": 160,
    "mpg_city": 23,
    "mpg_highway": 29,
    "": "",
    "__1": ""
  },
  {
    "car": 0,
    "year": 2005,
    "firm_id": 3,
    "firm_name": "HONDA",
    "division": "Honda",
    "model": "Element",
    "hybrid": 0,
    "segm1": 38,
    "Quantity": 56262,
    "Price": 16615,
    "wheel_base": 101.4,
    "length": 166.5,
    "width": 71.5,
    "weight": 3331,
    "disp": 2.4,
    "hp": 160,
    "mpg_city": 21,
    "mpg_highway": 26,
    "": "",
    "__1": ""
  },
  {
    "car": 0,
    "year": 2005,
    "firm_id": 3,
    "firm_name": "HONDA",
    "division": "Honda",
    "model": "Odyssey",
    "hybrid": 0,
    "segm1": 21,
    "Quantity": 174275,
    "Price": 25510,
    "wheel_base": 118.1,
    "length": 201.2,
    "width": 75.6,
    "weight": 4378,
    "disp": 3.5,
    "hp": 255,
    "mpg_city": 19,
    "mpg_highway": 25,
    "": "",
    "__1": ""
  },
  {
    "car": 0,
    "year": 2005,
    "firm_id": 3,
    "firm_name": "HONDA",
    "division": "Honda",
    "model": "Pilot",
    "hybrid": 0,
    "segm1": 38,
    "Quantity": 143353,
    "Price": 27865,
    "wheel_base": 106.3,
    "length": 188,
    "width": 77.3,
    "weight": 4414,
    "disp": 3.5,
    "hp": 255,
    "mpg_city": 17,
    "mpg_highway": 22,
    "": "",
    "__1": ""
  },
  {
    "car": 0,
    "year": 2005,
    "firm_id": 19,
    "firm_name": "GM",
    "division": "Hummer",
    "model": "HUMME2",
    "hybrid": 0,
    "segm1": 34,
    "Quantity": 23213,
    "Price": 52000,
    "wheel_base": 122.8,
    "length": 203.5,
    "width": 81.2,
    "weight": 6400,
    "disp": 6,
    "hp": 325,
    "mpg_city": 12,
    "mpg_highway": 15,
    "": "",
    "__1": ""
  },
  {
    "car": 0,
    "year": 2005,
    "firm_id": 21,
    "firm_name": "HYUNDAI",
    "division": "Hyundai",
    "model": "Santa Fe",
    "hybrid": 0,
    "segm1": 38,
    "Quantity": 68006,
    "Price": 22094,
    "wheel_base": 103.1,
    "length": 177.2,
    "width": 72.7,
    "weight": 3549,
    "disp": 2.7,
    "hp": 170,
    "mpg_city": 19,
    "mpg_highway": 25,
    "": "",
    "__1": ""
  },
  {
    "car": 0,
    "year": 2005,
    "firm_id": 21,
    "firm_name": "HYUNDAI",
    "division": "Hyundai",
    "model": "Tucson",
    "hybrid": 0,
    "segm1": 38,
    "Quantity": 61048,
    "Price": 18094,
    "wheel_base": 103.5,
    "length": 170.3,
    "width": 70.7,
    "weight": 3240,
    "disp": 2,
    "hp": 140,
    "mpg_city": 22,
    "mpg_highway": 27,
    "": "",
    "__1": ""
  },
  {
    "car": 0,
    "year": 2005,
    "firm_id": 2,
    "firm_name": "NISSAN",
    "division": "Infiniti",
    "model": "Fx",
    "hybrid": 0,
    "segm1": 39,
    "Quantity": 26786,
    "Price": 35340,
    "wheel_base": 112.2,
    "length": 189.1,
    "width": 75.8,
    "weight": 4110,
    "disp": 3.5,
    "hp": 280,
    "mpg_city": 17,
    "mpg_highway": 23,
    "": "",
    "__1": ""
  },
  {
    "car": 0,
    "year": 2005,
    "firm_id": 2,
    "firm_name": "NISSAN",
    "division": "Infiniti",
    "model": "QX56",
    "hybrid": 0,
    "segm1": 34,
    "Quantity": 14711,
    "Price": 48430,
    "wheel_base": 123.2,
    "length": 206.9,
    "width": 78.8,
    "weight": 5360,
    "disp": 5.6,
    "hp": 315,
    "mpg_city": 13,
    "mpg_highway": 19,
    "": "",
    "__1": ""
  },
  {
    "car": 0,
    "year": 2005,
    "firm_id": 13,
    "firm_name": "ISUZU",
    "division": "Isuzu",
    "model": "Ascender",
    "hybrid": 0,
    "segm1": 32,
    "Quantity": 7585,
    "Price": 29254,
    "wheel_base": 129,
    "length": 207.6,
    "width": 76.1,
    "weight": 4790,
    "disp": 4.2,
    "hp": 275,
    "mpg_city": 15,
    "mpg_highway": 19,
    "": "",
    "__1": ""
  },
  {
    "car": 0,
    "year": 2005,
    "firm_id": 16,
    "firm_name": "CHRYSLER",
    "division": "Jeep",
    "model": "Grand Cherokee",
    "hybrid": 0,
    "segm1": 32,
    "Quantity": 213584,
    "Price": 26775,
    "wheel_base": 109.5,
    "length": 186.6,
    "width": 84.3,
    "weight": 4254,
    "disp": 3.7,
    "hp": 210,
    "mpg_city": 16,
    "mpg_highway": 21,
    "": "",
    "__1": ""
  },
  {
    "car": 0,
    "year": 2005,
    "firm_id": 16,
    "firm_name": "CHRYSLER",
    "division": "Jeep",
    "model": "Liberty",
    "hybrid": 0,
    "segm1": 31,
    "Quantity": 166883,
    "Price": 19800,
    "wheel_base": 104.3,
    "length": 174.4,
    "width": 71.6,
    "weight": 3648,
    "disp": 2.4,
    "hp": 150,
    "mpg_city": 20,
    "mpg_highway": 24,
    "": "",
    "__1": ""
  },
  {
    "car": 0,
    "year": 2005,
    "firm_id": 16,
    "firm_name": "CHRYSLER",
    "division": "Jeep",
    "model": "Wrangler",
    "hybrid": 0,
    "segm1": 31,
    "Quantity": 79017,
    "Price": 18510,
    "wheel_base": 93.4,
    "length": 150.2,
    "width": 71.2,
    "weight": 3200,
    "disp": 2.4,
    "hp": 147,
    "mpg_city": 18,
    "mpg_highway": 20,
    "": "",
    "__1": ""
  },
  {
    "car": 0,
    "year": 2005,
    "firm_id": 30,
    "firm_name": "KIA",
    "division": "Kia",
    "model": "Sedona",
    "hybrid": 0,
    "segm1": 21,
    "Quantity": 52837,
    "Price": 20840,
    "wheel_base": 114.6,
    "length": 194.1,
    "width": 74.6,
    "weight": 4802,
    "disp": 3.5,
    "hp": 195,
    "mpg_city": 16,
    "mpg_highway": 22,
    "": "",
    "__1": ""
  },
  {
    "car": 0,
    "year": 2005,
    "firm_id": 30,
    "firm_name": "KIA",
    "division": "Kia",
    "model": "Sorento",
    "hybrid": 0,
    "segm1": 32,
    "Quantity": 47610,
    "Price": 19635,
    "wheel_base": 106.7,
    "length": 179.8,
    "width": 73.3,
    "weight": 4112,
    "disp": 3.5,
    "hp": 192,
    "mpg_city": 16,
    "mpg_highway": 19,
    "": "",
    "__1": ""
  },
  {
    "car": 0,
    "year": 2005,
    "firm_id": 32,
    "firm_name": "LAND",
    "division": "Land Rover",
    "model": "Freelander",
    "hybrid": 0,
    "segm1": 32,
    "Quantity": 2141,
    "Price": 27495,
    "wheel_base": 101.1,
    "length": 174.1,
    "width": 81.5,
    "weight": 3640,
    "disp": 2.5,
    "hp": 174,
    "mpg_city": 17,
    "mpg_highway": 21,
    "": "",
    "__1": ""
  },
  {
    "car": 0,
    "year": 2005,
    "firm_id": 32,
    "firm_name": "LAND",
    "division": "Land Rover",
    "model": "LR3",
    "hybrid": 0,
    "segm1": 32,
    "Quantity": 19346,
    "Price": 44995,
    "wheel_base": 113.6,
    "length": 190.9,
    "width": 75.4,
    "weight": 5426,
    "disp": 4.4,
    "hp": 300,
    "mpg_city": 14,
    "mpg_highway": 18,
    "": "",
    "__1": ""
  },
  {
    "car": 0,
    "year": 2005,
    "firm_id": 1,
    "firm_name": "TOYOTA",
    "division": "Lexus",
    "model": "GX470",
    "hybrid": 0,
    "segm1": 38,
    "Quantity": 34339,
    "Price": 46425,
    "wheel_base": 109.8,
    "length": 188.2,
    "width": 74,
    "weight": 4871,
    "disp": 4.7,
    "hp": 270,
    "mpg_city": 15,
    "mpg_highway": 19,
    "": "",
    "__1": ""
  },
  {
    "car": 0,
    "year": 2005,
    "firm_id": 1,
    "firm_name": "TOYOTA",
    "division": "Lexus",
    "model": "LX450 LX470",
    "hybrid": 0,
    "segm1": 34,
    "Quantity": 8555,
    "Price": 65400,
    "wheel_base": 112.2,
    "length": 192.5,
    "width": 76.4,
    "weight": 5900,
    "disp": 4.7,
    "hp": 235,
    "mpg_city": 13,
    "mpg_highway": 17,
    "": "",
    "__1": ""
  },
  {
    "car": 0,
    "year": 2005,
    "firm_id": 1,
    "firm_name": "TOYOTA",
    "division": "Lexus",
    "model": "RX330",
    "hybrid": 0,
    "segm1": 39,
    "Quantity": 108775,
    "Price": 36400,
    "wheel_base": 106.9,
    "length": 186.2,
    "width": 72.6,
    "weight": 3860,
    "disp": 3.3,
    "hp": 230,
    "mpg_city": 19,
    "mpg_highway": 25,
    "": "",
    "__1": ""
  },
  {
    "car": 0,
    "year": 2005,
    "firm_id": 18,
    "firm_name": "FORD",
    "division": "Lincoln",
    "model": "Aviator",
    "hybrid": 0,
    "segm1": 34,
    "Quantity": 15873,
    "Price": 41200,
    "wheel_base": 113.7,
    "length": 193.3,
    "width": 73.9,
    "weight": 4818,
    "disp": 4.6,
    "hp": 302,
    "mpg_city": 13,
    "mpg_highway": 18,
    "": "",
    "__1": ""
  },
  {
    "car": 0,
    "year": 2005,
    "firm_id": 18,
    "firm_name": "FORD",
    "division": "Lincoln",
    "model": "Navigator",
    "hybrid": 0,
    "segm1": 34,
    "Quantity": 25844,
    "Price": 50435,
    "wheel_base": 118.8,
    "length": 207.5,
    "width": 78.7,
    "weight": 5555,
    "disp": 5.4,
    "hp": 300,
    "mpg_city": 13,
    "mpg_highway": 18,
    "": "",
    "__1": ""
  },
  {
    "car": 0,
    "year": 2005,
    "firm_id": 18,
    "firm_name": "FORD",
    "division": "lincoln mercury",
    "model": "Mariner",
    "hybrid": 0,
    "segm1": 38,
    "Quantity": 34099,
    "Price": 21995,
    "wheel_base": 103.1,
    "length": 174.3,
    "width": 70.1,
    "weight": 3285,
    "disp": 2.3,
    "hp": 153,
    "mpg_city": 22,
    "mpg_highway": 26,
    "": "",
    "__1": ""
  },
  {
    "car": 0,
    "year": 2005,
    "firm_id": 18,
    "firm_name": "FORD",
    "division": "lincoln mercury",
    "model": "Monterey",
    "hybrid": 0,
    "segm1": 22,
    "Quantity": 8166,
    "Price": 29695,
    "wheel_base": 120.8,
    "length": 201,
    "width": 76.4,
    "weight": 4434,
    "disp": 4.2,
    "hp": 201,
    "mpg_city": 17,
    "mpg_highway": 23,
    "": "",
    "__1": ""
  },
  {
    "car": 0,
    "year": 2005,
    "firm_id": 18,
    "firm_name": "FORD",
    "division": "lincoln mercury",
    "model": "Mountaineer",
    "hybrid": 0,
    "segm1": 32,
    "Quantity": 32491,
    "Price": 29995,
    "wheel_base": 113.8,
    "length": 190.9,
    "width": 72.3,
    "weight": 4414,
    "disp": 4,
    "hp": 210,
    "mpg_city": 16,
    "mpg_highway": 21,
    "": "",
    "__1": ""
  },
  {
    "car": 0,
    "year": 2005,
    "firm_id": 4,
    "firm_name": "MAZDA",
    "division": "Mazda",
    "model": "B-series",
    "hybrid": 0,
    "segm1": 41,
    "Quantity": 5872,
    "Price": 15935,
    "wheel_base": 111.6,
    "length": 187.5,
    "width": 69.4,
    "weight": 3994,
    "disp": 2.3,
    "hp": 143,
    "mpg_city": 24,
    "mpg_highway": 29,
    "": "",
    "__1": ""
  },
  {
    "car": 0,
    "year": 2005,
    "firm_id": 4,
    "firm_name": "MAZDA",
    "division": "Mazda",
    "model": "MPV",
    "hybrid": 0,
    "segm1": 21,
    "Quantity": 17634,
    "Price": 23485,
    "wheel_base": 111.8,
    "length": 189.5,
    "width": 72.1,
    "weight": 3772,
    "disp": 3,
    "hp": 200,
    "mpg_city": 18,
    "mpg_highway": 25,
    "": "",
    "__1": ""
  },
  {
    "car": 0,
    "year": 2005,
    "firm_id": 4,
    "firm_name": "MAZDA",
    "division": "Mazda",
    "model": "Tribute",
    "hybrid": 0,
    "segm1": 38,
    "Quantity": 36761,
    "Price": 20220,
    "wheel_base": 103.1,
    "length": 174.4,
    "width": 72,
    "weight": 3181,
    "disp": 2.3,
    "hp": 153,
    "mpg_city": 24,
    "mpg_highway": 29,
    "": "",
    "__1": ""
  },
  {
    "car": 0,
    "year": 2005,
    "firm_id": 9,
    "firm_name": "MERCEDEZ",
    "division": "MERCEDEZ",
    "model": "G class",
    "hybrid": 0,
    "segm1": 34,
    "Quantity": 1334,
    "Price": 78420,
    "wheel_base": 112.2,
    "length": 185.6,
    "width": 71.3,
    "weight": 5545,
    "disp": 5,
    "hp": 292,
    "mpg_city": 13,
    "mpg_highway": 14,
    "": "",
    "__1": ""
  },
  {
    "car": 0,
    "year": 2005,
    "firm_id": 9,
    "firm_name": "MERCEDEZ",
    "division": "MERCEDEZ",
    "model": "ML320",
    "hybrid": 0,
    "segm1": 39,
    "Quantity": 34959,
    "Price": 38670,
    "wheel_base": 111,
    "length": 182.6,
    "width": 72.4,
    "weight": 4819,
    "disp": 3.7,
    "hp": 232,
    "mpg_city": 15,
    "mpg_highway": 18,
    "": "",
    "__1": ""
  },
  {
    "car": 0,
    "year": 2005,
    "firm_id": 10,
    "firm_name": "MITSUBIS",
    "division": "Mitsubishi",
    "model": "Endeavor",
    "hybrid": 0,
    "segm1": 38,
    "Quantity": 20994,
    "Price": 25994,
    "wheel_base": 108.3,
    "length": 190.2,
    "width": 73.6,
    "weight": 3869,
    "disp": 3.8,
    "hp": 225,
    "mpg_city": 17,
    "mpg_highway": 23,
    "": "",
    "__1": ""
  },
  {
    "car": 0,
    "year": 2005,
    "firm_id": 10,
    "firm_name": "MITSUBIS",
    "division": "Mitsubishi",
    "model": "Montero",
    "hybrid": 0,
    "segm1": 32,
    "Quantity": 2778,
    "Price": 35799,
    "wheel_base": 109.7,
    "length": 190.2,
    "width": 74.8,
    "weight": 4787,
    "disp": 3.8,
    "hp": 215,
    "mpg_city": 15,
    "mpg_highway": 19,
    "": "",
    "__1": ""
  },
  {
    "car": 0,
    "year": 2005,
    "firm_id": 10,
    "firm_name": "MITSUBIS",
    "division": "Mitsubishi",
    "model": "Outlander",
    "hybrid": 0,
    "segm1": 38,
    "Quantity": 11848,
    "Price": 18394,
    "wheel_base": 103.3,
    "length": 179.1,
    "width": 68.9,
    "weight": 3240,
    "disp": 2.4,
    "hp": 160,
    "mpg_city": 22,
    "mpg_highway": 28,
    "": "",
    "__1": ""
  },
  {
    "car": 0,
    "year": 2005,
    "firm_id": 2,
    "firm_name": "NISSAN",
    "division": "Nissan",
    "model": "Armada",
    "hybrid": 0,
    "segm1": 39,
    "Quantity": 39508,
    "Price": 34250,
    "wheel_base": 123.2,
    "length": 206.9,
    "width": 78.8,
    "weight": 5168,
    "disp": 5.6,
    "hp": 305,
    "mpg_city": 13,
    "mpg_highway": 19,
    "": "",
    "__1": ""
  },
  {
    "car": 0,
    "year": 2005,
    "firm_id": 2,
    "firm_name": "NISSAN",
    "division": "Nissan",
    "model": "Frontier",
    "hybrid": 0,
    "segm1": 41,
    "Quantity": 72838,
    "Price": 16080,
    "wheel_base": 125.9,
    "length": 205.5,
    "width": 72.8,
    "weight": 3675,
    "disp": 2.5,
    "hp": 154,
    "mpg_city": 22,
    "mpg_highway": 25,
    "": "",
    "__1": ""
  },
  {
    "car": 0,
    "year": 2005,
    "firm_id": 2,
    "firm_name": "NISSAN",
    "division": "Nissan",
    "model": "Murano",
    "hybrid": 0,
    "segm1": 38,
    "Quantity": 74454,
    "Price": 27500,
    "wheel_base": 111.2,
    "length": 187.6,
    "width": 74,
    "weight": 2269,
    "disp": 3.5,
    "hp": 245,
    "mpg_city": 20,
    "mpg_highway": 25,
    "": "",
    "__1": ""
  },
  {
    "car": 0,
    "year": 2005,
    "firm_id": 2,
    "firm_name": "NISSAN",
    "division": "Nissan",
    "model": "Pathfinder",
    "hybrid": 0,
    "segm1": 32,
    "Quantity": 76000,
    "Price": 25210,
    "wheel_base": 112.2,
    "length": 187.6,
    "width": 72.8,
    "weight": 4376,
    "disp": 4,
    "hp": 270,
    "mpg_city": 16,
    "mpg_highway": 23,
    "": "",
    "__1": ""
  },
  {
    "car": 0,
    "year": 2005,
    "firm_id": 2,
    "firm_name": "NISSAN",
    "division": "Nissan",
    "model": "Quest",
    "hybrid": 0,
    "segm1": 21,
    "Quantity": 40357,
    "Price": 23910,
    "wheel_base": 124,
    "length": 204.1,
    "width": 77.6,
    "weight": 4040,
    "disp": 3.5,
    "hp": 240,
    "mpg_city": 19,
    "mpg_highway": 26,
    "": "",
    "__1": ""
  },
  {
    "car": 0,
    "year": 2005,
    "firm_id": 2,
    "firm_name": "NISSAN",
    "division": "Nissan",
    "model": "Titan",
    "hybrid": 0,
    "segm1": 42,
    "Quantity": 86945,
    "Price": 23300,
    "wheel_base": 139.8,
    "length": 224.2,
    "width": 78.8,
    "weight": 5019,
    "disp": 5.6,
    "hp": 305,
    "mpg_city": 14,
    "mpg_highway": 19,
    "": "",
    "__1": ""
  },
  {
    "car": 0,
    "year": 2005,
    "firm_id": 2,
    "firm_name": "NISSAN",
    "division": "Nissan",
    "model": "Xterra",
    "hybrid": 0,
    "segm1": 31,
    "Quantity": 72447,
    "Price": 23300,
    "wheel_base": 106.3,
    "length": 178.7,
    "width": 72.8,
    "weight": 4081,
    "disp": 4,
    "hp": 265,
    "mpg_city": 14,
    "mpg_highway": 19,
    "": "",
    "__1": ""
  },
  {
    "car": 0,
    "year": 2005,
    "firm_id": 19,
    "firm_name": "GM",
    "division": "Pontiac",
    "model": "Aztek",
    "hybrid": 0,
    "segm1": 38,
    "Quantity": 5020,
    "Price": 22060,
    "wheel_base": 108.3,
    "length": 182.2,
    "width": 73.6,
    "weight": 3779,
    "disp": 3.4,
    "hp": 185,
    "mpg_city": 19,
    "mpg_highway": 26,
    "": "",
    "__1": ""
  },
  {
    "car": 0,
    "year": 2005,
    "firm_id": 19,
    "firm_name": "GM",
    "division": "Pontiac",
    "model": "MONTANA TRANS SPORT Sport",
    "hybrid": 0,
    "segm1": 21,
    "Quantity": 23439,
    "Price": 25235,
    "wheel_base": 121.1,
    "length": 205.5,
    "width": 72,
    "weight": 4206,
    "disp": 3.5,
    "hp": 200,
    "mpg_city": 18,
    "mpg_highway": 24,
    "": "",
    "__1": ""
  },
  {
    "car": 0,
    "year": 2005,
    "firm_id": 12,
    "firm_name": "PORSCHE",
    "division": "Porsche",
    "model": "Cayenne",
    "hybrid": 0,
    "segm1": 39,
    "Quantity": 13607,
    "Price": 41915,
    "wheel_base": 112.4,
    "length": 188.3,
    "width": 75.9,
    "weight": 4949,
    "disp": 3.2,
    "hp": 247,
    "mpg_city": 16,
    "mpg_highway": 20,
    "": "",
    "__1": ""
  },
  {
    "car": 0,
    "year": 2005,
    "firm_id": 19,
    "firm_name": "GM",
    "division": "SATURN",
    "model": "Vue",
    "hybrid": 0,
    "segm1": 38,
    "Quantity": 91972,
    "Price": 17630,
    "wheel_base": 106.6,
    "length": 181.3,
    "width": 71.6,
    "weight": 3207,
    "disp": 2.2,
    "hp": 143,
    "mpg_city": 23,
    "mpg_highway": 28,
    "": "",
    "__1": ""
  },
  {
    "car": 0,
    "year": 2005,
    "firm_id": 5,
    "firm_name": "SUBARU",
    "division": "SUBARU",
    "model": "baja",
    "hybrid": 0,
    "segm1": 38,
    "Quantity": 6239,
    "Price": 24770,
    "wheel_base": 104.3,
    "length": 193.3,
    "width": 70.1,
    "weight": 3485,
    "disp": 2.5,
    "hp": 210,
    "mpg_city": 19,
    "mpg_highway": 25,
    "": "",
    "__1": ""
  },
  {
    "car": 0,
    "year": 2005,
    "firm_id": 5,
    "firm_name": "SUBARU",
    "division": "subaru",
    "model": "forester",
    "hybrid": 0,
    "segm1": 38,
    "Quantity": 53541,
    "Price": 21870,
    "wheel_base": 99.4,
    "length": 175.2,
    "width": 68.3,
    "weight": 3090,
    "disp": 2.5,
    "hp": 165,
    "mpg_city": 23,
    "mpg_highway": 30,
    "": "",
    "__1": ""
  },
  {
    "car": 0,
    "year": 2005,
    "firm_id": 31,
    "firm_name": "SUZUKI",
    "division": "Suzuki",
    "model": "Grand Vitara",
    "hybrid": 0,
    "segm1": 31,
    "Quantity": 8624,
    "Price": 18994,
    "wheel_base": 97.6,
    "length": 164.6,
    "width": 70.1,
    "weight": 3108,
    "disp": 2.5,
    "hp": 165,
    "mpg_city": 19,
    "mpg_highway": 22,
    "": "",
    "__1": ""
  },
  {
    "car": 0,
    "year": 2005,
    "firm_id": 1,
    "firm_name": "TOYOTA",
    "division": "Toyota",
    "model": "4 Runner",
    "hybrid": 0,
    "segm1": 32,
    "Quantity": 103830,
    "Price": 28060,
    "wheel_base": 109.8,
    "length": 189,
    "width": 73.8,
    "weight": 4045,
    "disp": 4,
    "hp": 245,
    "mpg_city": 18,
    "mpg_highway": 21,
    "": "",
    "__1": ""
  },
  {
    "car": 0,
    "year": 2005,
    "firm_id": 1,
    "firm_name": "TOYOTA",
    "division": "Toyota",
    "model": "Highlander",
    "hybrid": 0,
    "segm1": 38,
    "Quantity": 137409,
    "Price": 24645,
    "wheel_base": 106.9,
    "length": 184.4,
    "width": 71.9,
    "weight": 3520,
    "disp": 2.4,
    "hp": 160,
    "mpg_city": 22,
    "mpg_highway": 27,
    "": "",
    "__1": ""
  },
  {
    "car": 0,
    "year": 2005,
    "firm_id": 1,
    "firm_name": "TOYOTA",
    "division": "Toyota",
    "model": "Land Cruiser",
    "hybrid": 0,
    "segm1": 34,
    "Quantity": 4870,
    "Price": 55590,
    "wheel_base": 112.2,
    "length": 192.5,
    "width": 76.4,
    "weight": 5390,
    "disp": 4.7,
    "hp": 235,
    "mpg_city": 13,
    "mpg_highway": 17,
    "": "",
    "__1": ""
  },
  {
    "car": 0,
    "year": 2005,
    "firm_id": 1,
    "firm_name": "TOYOTA",
    "division": "Toyota",
    "model": "RAV4",
    "hybrid": 0,
    "segm1": 38,
    "Quantity": 70518,
    "Price": 19115,
    "wheel_base": 98,
    "length": 166.6,
    "width": 68.3,
    "weight": 2897,
    "disp": 2.4,
    "hp": 161,
    "mpg_city": 24,
    "mpg_highway": 30,
    "": "",
    "__1": ""
  },
  {
    "car": 0,
    "year": 2005,
    "firm_id": 1,
    "firm_name": "TOYOTA",
    "division": "Toyota",
    "model": "Sequoia",
    "hybrid": 0,
    "segm1": 33,
    "Quantity": 45905,
    "Price": 33035,
    "wheel_base": 118.1,
    "length": 203.9,
    "width": 78.9,
    "weight": 4875,
    "disp": 4.7,
    "hp": 282,
    "mpg_city": 15,
    "mpg_highway": 18,
    "": "",
    "__1": ""
  },
  {
    "car": 0,
    "year": 2005,
    "firm_id": 1,
    "firm_name": "TOYOTA",
    "division": "Toyota",
    "model": "Sienna",
    "hybrid": 0,
    "segm1": 21,
    "Quantity": 161380,
    "Price": 23790,
    "wheel_base": 119.3,
    "length": 200,
    "width": 77.4,
    "weight": 4210,
    "disp": 3.3,
    "hp": 230,
    "mpg_city": 19,
    "mpg_highway": 27,
    "": "",
    "__1": ""
  },
  {
    "car": 0,
    "year": 2005,
    "firm_id": 1,
    "firm_name": "TOYOTA",
    "division": "Toyota",
    "model": "Tacoma",
    "hybrid": 0,
    "segm1": 41,
    "Quantity": 168831,
    "Price": 13980,
    "wheel_base": 109.4,
    "length": 190.4,
    "width": 72.2,
    "weight": 3140,
    "disp": 2.7,
    "hp": 164,
    "mpg_city": 20,
    "mpg_highway": 27,
    "": "",
    "__1": ""
  },
  {
    "car": 0,
    "year": 2005,
    "firm_id": 1,
    "firm_name": "TOYOTA",
    "division": "Toyota",
    "model": "Tundra",
    "hybrid": 0,
    "segm1": 42,
    "Quantity": 126529,
    "Price": 16520,
    "wheel_base": 128.3,
    "length": 218.3,
    "width": 75.2,
    "weight": 3935,
    "disp": 4,
    "hp": 245,
    "mpg_city": 17,
    "mpg_highway": 21,
    "": "",
    "__1": ""
  },
  {
    "car": 0,
    "year": 2005,
    "firm_id": 59,
    "firm_name": "TOYOTA",
    "division": "TOYOTA",
    "model": "scion xb",
    "hybrid": 0,
    "segm1": 31,
    "Quantity": 54037,
    "Price": 14195,
    "wheel_base": 98.4,
    "length": 155.3,
    "width": 66.5,
    "weight": 2395,
    "disp": 1.5,
    "hp": 108,
    "mpg_city": 30,
    "mpg_highway": 34,
    "": "",
    "__1": ""
  },
  {
    "car": 0,
    "year": 2005,
    "firm_id": 7,
    "firm_name": "VOLKS",
    "division": "volkswagen",
    "model": "Touareg",
    "hybrid": 0,
    "segm1": 39,
    "Quantity": 18050,
    "Price": 37755,
    "wheel_base": 112.4,
    "length": 187.2,
    "width": 75.9,
    "weight": 5086,
    "disp": 3.2,
    "hp": 240,
    "mpg_city": 15,
    "mpg_highway": 20,
    "": "",
    "__1": ""
  },
  {
    "car": 0,
    "year": 2005,
    "firm_id": 6,
    "firm_name": "VOLVO",
    "division": "Volvo",
    "model": "XC90",
    "hybrid": 0,
    "segm1": 39,
    "Quantity": 35976,
    "Price": 35525,
    "wheel_base": 112.6,
    "length": 188.9,
    "width": 74.4,
    "weight": 4450,
    "disp": 2.5,
    "hp": 208,
    "mpg_city": 18,
    "mpg_highway": 24,
    "": "",
    "__1": ""
  },
  {
    "car": 1,
    "year": 2005,
    "firm_id": 3,
    "firm_name": "HONDA",
    "division": "acura",
    "model": "RSX",
    "hybrid": 0,
    "segm1": 2,
    "Quantity": 20809,
    "Price": 20745,
    "wheel_base": 101.2,
    "length": 172.2,
    "width": 67.9,
    "weight": 2734,
    "disp": 2,
    "hp": 160,
    "mpg_city": 27,
    "mpg_highway": 34,
    "": "",
    "__1": ""
  },
  {
    "car": 1,
    "year": 2005,
    "firm_id": 3,
    "firm_name": "HONDA",
    "division": "acura",
    "model": "RL",
    "hybrid": 0,
    "segm1": 5,
    "Quantity": 17572,
    "Price": 49470,
    "wheel_base": 110.2,
    "length": 193.6,
    "width": 72.7,
    "weight": 3984,
    "disp": 3.5,
    "hp": 300,
    "mpg_city": 18,
    "mpg_highway": 26,
    "": "",
    "__1": ""
  },
  {
    "car": 1,
    "year": 2005,
    "firm_id": 3,
    "firm_name": "HONDA",
    "division": "acura",
    "model": "TL",
    "hybrid": 0,
    "segm1": 5,
    "Quantity": 78218,
    "Price": 33470,
    "wheel_base": 107.9,
    "length": 189.3,
    "width": 72.2,
    "weight": 3483,
    "disp": 3.2,
    "hp": 270,
    "mpg_city": 20,
    "mpg_highway": 29,
    "": "",
    "__1": ""
  },
  {
    "car": 1,
    "year": 2005,
    "firm_id": 3,
    "firm_name": "HONDA",
    "division": "acura",
    "model": "TSX",
    "hybrid": 0,
    "segm1": 3,
    "Quantity": 34856,
    "Price": 27060,
    "wheel_base": 105.1,
    "length": 183.3,
    "width": 69.4,
    "weight": 3230,
    "disp": 2.4,
    "hp": 200,
    "mpg_city": 22,
    "mpg_highway": 30,
    "": "",
    "__1": ""
  },
  {
    "car": 1,
    "year": 2005,
    "firm_id": 7,
    "firm_name": "VOLKS",
    "division": "audi",
    "model": "A6",
    "hybrid": 0,
    "segm1": 5,
    "Quantity": 18074,
    "Price": 41620,
    "wheel_base": 111.9,
    "length": 193.5,
    "width": 79.2,
    "weight": 3957,
    "disp": 3.2,
    "hp": 255,
    "mpg_city": 17,
    "mpg_highway": 23,
    "": "",
    "__1": ""
  },
  {
    "car": 1,
    "year": 2005,
    "firm_id": 7,
    "firm_name": "VOLKS",
    "division": "audi",
    "model": "A8",
    "hybrid": 0,
    "segm1": 5,
    "Quantity": 5430,
    "Price": 70620,
    "wheel_base": 121.1,
    "length": 204,
    "width": 74.6,
    "weight": 4399,
    "disp": 4.2,
    "hp": 335,
    "mpg_city": 18,
    "mpg_highway": 24,
    "": "",
    "__1": ""
  },
  {
    "car": 1,
    "year": 2005,
    "firm_id": 7,
    "firm_name": "VOLKS",
    "division": "audi",
    "model": "allroad",
    "hybrid": 0,
    "segm1": 5,
    "Quantity": 2429,
    "Price": 40970,
    "wheel_base": 108.5,
    "length": 189.4,
    "width": 76.1,
    "weight": 4167,
    "disp": 2.7,
    "hp": 250,
    "mpg_city": 16,
    "mpg_highway": 23,
    "": "",
    "__1": ""
  },
  {
    "car": 1,
    "year": 2005,
    "firm_id": 7,
    "firm_name": "VOLKS",
    "division": "audi",
    "model": "TT",
    "hybrid": 0,
    "segm1": 5,
    "Quantity": 2822,
    "Price": 34220,
    "wheel_base": 95.4,
    "length": 159.1,
    "width": 73.1,
    "weight": 2987,
    "disp": 1.8,
    "hp": 180,
    "mpg_city": 20,
    "mpg_highway": 28,
    "": "",
    "__1": ""
  },
  {
    "car": 1,
    "year": 2005,
    "firm_id": 7,
    "firm_name": "VOLKS",
    "division": "audi",
    "model": "A4",
    "hybrid": 0,
    "segm1": 2,
    "Quantity": 48922,
    "Price": 26520,
    "wheel_base": 104.3,
    "length": 179,
    "width": 76.3,
    "weight": 3252,
    "disp": 1.8,
    "hp": 170,
    "mpg_city": 23,
    "mpg_highway": 30,
    "": "",
    "__1": ""
  },
  {
    "car": 1,
    "year": 2005,
    "firm_id": 8,
    "firm_name": "BMW",
    "division": "bmw",
    "model": "325i",
    "hybrid": 0,
    "segm1": 2,
    "Quantity": 106950,
    "Price": 29995,
    "wheel_base": 107.3,
    "length": 176,
    "width": 68.5,
    "weight": 3219,
    "disp": 2.5,
    "hp": 184,
    "mpg_city": 20,
    "mpg_highway": 29,
    "": "",
    "__1": ""
  },
  {
    "car": 1,
    "year": 2005,
    "firm_id": 8,
    "firm_name": "BMW",
    "division": "bmw",
    "model": "525i",
    "hybrid": 0,
    "segm1": 5,
    "Quantity": 52722,
    "Price": 41995,
    "wheel_base": 113.7,
    "length": 190.6,
    "width": 72.7,
    "weight": 3417,
    "disp": 2.5,
    "hp": 184,
    "mpg_city": 19,
    "mpg_highway": 28,
    "": "",
    "__1": ""
  },
  {
    "car": 1,
    "year": 2005,
    "firm_id": 8,
    "firm_name": "BMW",
    "division": "bmw",
    "model": "745i",
    "hybrid": 0,
    "segm1": 5,
    "Quantity": 18165,
    "Price": 70595,
    "wheel_base": 117.7,
    "length": 198,
    "width": 74.9,
    "weight": 4376,
    "disp": 4.4,
    "hp": 325,
    "mpg_city": 18,
    "mpg_highway": 26,
    "": "",
    "__1": ""
  },
  {
    "car": 1,
    "year": 2005,
    "firm_id": 8,
    "firm_name": "BMW",
    "division": "bmw",
    "model": "z4",
    "hybrid": 0,
    "segm1": 5,
    "Quantity": 10045,
    "Price": 34995,
    "wheel_base": 98.2,
    "length": 161.1,
    "width": 70.1,
    "weight": 2932,
    "disp": 2.5,
    "hp": 184,
    "mpg_city": 21,
    "mpg_highway": 28,
    "": "",
    "__1": ""
  },
  {
    "car": 1,
    "year": 2005,
    "firm_id": 19,
    "firm_name": "GM",
    "division": "buick",
    "model": "lacrosse",
    "hybrid": 0,
    "segm1": 4,
    "Quantity": 92669,
    "Price": 23495,
    "wheel_base": 110.5,
    "length": 198.1,
    "width": 73,
    "weight": 3585,
    "disp": 3.8,
    "hp": 200,
    "mpg_city": 20,
    "mpg_highway": 27,
    "": "",
    "__1": ""
  },
  {
    "car": 1,
    "year": 2005,
    "firm_id": 19,
    "firm_name": "GM",
    "division": "buick",
    "model": "lesabre",
    "hybrid": 0,
    "segm1": 4,
    "Quantity": 75369,
    "Price": 27270,
    "wheel_base": 112.2,
    "length": 200,
    "width": 73.5,
    "weight": 3567,
    "disp": 3.8,
    "hp": 205,
    "mpg_city": 20,
    "mpg_highway": 29,
    "": "",
    "__1": ""
  },
  {
    "car": 1,
    "year": 2005,
    "firm_id": 19,
    "firm_name": "GM",
    "division": "cadillac",
    "model": "CTS DTS DTS",
    "hybrid": 0,
    "segm1": 5,
    "Quantity": 61512,
    "Price": 31060,
    "wheel_base": 113.4,
    "length": 190.1,
    "width": 70.6,
    "weight": 3568,
    "disp": 3.2,
    "hp": 220,
    "mpg_city": 18,
    "mpg_highway": 27,
    "": "",
    "__1": ""
  },
  {
    "car": 1,
    "year": 2005,
    "firm_id": 19,
    "firm_name": "GM",
    "division": "cadillac",
    "model": "deville",
    "hybrid": 0,
    "segm1": 5,
    "Quantity": 38661,
    "Price": 46490,
    "wheel_base": 115.3,
    "length": 207.2,
    "width": 74.4,
    "weight": 3984,
    "disp": 4.6,
    "hp": 275,
    "mpg_city": 18,
    "mpg_highway": 24,
    "": "",
    "__1": ""
  },
  {
    "car": 1,
    "year": 2005,
    "firm_id": 19,
    "firm_name": "GM",
    "division": "cadillac",
    "model": "STS",
    "hybrid": 0,
    "segm1": 5,
    "Quantity": 33497,
    "Price": 40995,
    "wheel_base": 116.4,
    "length": 196.3,
    "width": 72.6,
    "weight": 3857,
    "disp": 3.6,
    "hp": 255,
    "mpg_city": 17,
    "mpg_highway": 24,
    "": "",
    "__1": ""
  },
  {
    "car": 1,
    "year": 2005,
    "firm_id": 19,
    "firm_name": "GM",
    "division": "chevrolet",
    "model": "cobalt",
    "hybrid": 0,
    "segm1": 2,
    "Quantity": 212667,
    "Price": 14190,
    "wheel_base": 103.3,
    "length": 180.5,
    "width": 67.9,
    "weight": 2868,
    "disp": 2.2,
    "hp": 145,
    "mpg_city": 25,
    "mpg_highway": 29,
    "": "",
    "__1": ""
  },
  {
    "car": 1,
    "year": 2005,
    "firm_id": 19,
    "firm_name": "GM",
    "division": "chevrolet",
    "model": "corvette",
    "hybrid": 0,
    "segm1": 5,
    "Quantity": 32489,
    "Price": 44245,
    "wheel_base": 106,
    "length": 175,
    "width": 73,
    "weight": 3179,
    "disp": 6,
    "hp": 400,
    "mpg_city": 18,
    "mpg_highway": 26,
    "": "",
    "__1": ""
  },
  {
    "car": 1,
    "year": 2005,
    "firm_id": 19,
    "firm_name": "GM",
    "division": "chevrolet",
    "model": "impala",
    "hybrid": 0,
    "segm1": 4,
    "Quantity": 246481,
    "Price": 22880,
    "wheel_base": 110.5,
    "length": 200,
    "width": 73,
    "weight": 3343,
    "disp": 3.4,
    "hp": 180,
    "mpg_city": 21,
    "mpg_highway": 32,
    "": "",
    "__1": ""
  },
  {
    "car": 1,
    "year": 2005,
    "firm_id": 19,
    "firm_name": "GM",
    "division": "chevrolet",
    "model": "malibu",
    "hybrid": 0,
    "segm1": 3,
    "Quantity": 203503,
    "Price": 19710,
    "wheel_base": 106.3,
    "length": 188.3,
    "width": 69.9,
    "weight": 3174,
    "disp": 2.2,
    "hp": 145,
    "mpg_city": 24,
    "mpg_highway": 35,
    "": "",
    "__1": ""
  },
  {
    "car": 1,
    "year": 2005,
    "firm_id": 19,
    "firm_name": "GM",
    "division": "chevrolet",
    "model": "monte carlo",
    "hybrid": 0,
    "segm1": 3,
    "Quantity": 33562,
    "Price": 22810,
    "wheel_base": 110.5,
    "length": 197.9,
    "width": 72.3,
    "weight": 3340,
    "disp": 3.4,
    "hp": 180,
    "mpg_city": 21,
    "mpg_highway": 32,
    "": "",
    "__1": ""
  },
  {
    "car": 1,
    "year": 2005,
    "firm_id": 16,
    "firm_name": "CHRYSLER",
    "division": "chrysler",
    "model": "300 series",
    "hybrid": 0,
    "segm1": 4,
    "Quantity": 144068,
    "Price": 29995,
    "wheel_base": 120,
    "length": 196.8,
    "width": 74.1,
    "weight": 3767,
    "disp": 3.5,
    "hp": 250,
    "mpg_city": 17,
    "mpg_highway": 24,
    "": "",
    "__1": ""
  },
  {
    "car": 1,
    "year": 2005,
    "firm_id": 16,
    "firm_name": "CHRYSLER",
    "division": "chrysler",
    "model": "crossfire",
    "hybrid": 0,
    "segm1": 5,
    "Quantity": 14665,
    "Price": 34620,
    "wheel_base": 94.5,
    "length": 159.8,
    "width": 69.5,
    "weight": 3060,
    "disp": 3.2,
    "hp": 215,
    "mpg_city": 21,
    "mpg_highway": 28,
    "": "",
    "__1": ""
  },
  {
    "car": 1,
    "year": 2005,
    "firm_id": 16,
    "firm_name": "CHRYSLER",
    "division": "chrysler",
    "model": "PT cruiser",
    "hybrid": 0,
    "segm1": 1,
    "Quantity": 133740,
    "Price": 19995,
    "wheel_base": 103,
    "length": 168.8,
    "width": 67.1,
    "weight": 3303,
    "disp": 2.4,
    "hp": 150,
    "mpg_city": 22,
    "mpg_highway": 26,
    "": "",
    "__1": ""
  },
  {
    "car": 1,
    "year": 2005,
    "firm_id": 16,
    "firm_name": "CHRYSLER",
    "division": "chrysler",
    "model": "sebring",
    "hybrid": 0,
    "segm1": 2,
    "Quantity": 90294,
    "Price": 22770,
    "wheel_base": 103.7,
    "length": 191.9,
    "width": 69.9,
    "weight": 3064,
    "disp": 2.4,
    "hp": 142,
    "mpg_city": 24,
    "mpg_highway": 28,
    "": "",
    "__1": ""
  },
  {
    "car": 1,
    "year": 2005,
    "firm_id": 16,
    "firm_name": "CHRYSLER",
    "division": "dodge",
    "model": "neon",
    "hybrid": 0,
    "segm1": 2,
    "Quantity": 113322,
    "Price": 14160,
    "wheel_base": 105,
    "length": 174.4,
    "width": 67.4,
    "weight": 2581,
    "disp": 2,
    "hp": 132,
    "mpg_city": 29,
    "mpg_highway": 32,
    "": "",
    "__1": ""
  },
  {
    "car": 1,
    "year": 2005,
    "firm_id": 16,
    "firm_name": "CHRYSLER",
    "division": "dodge",
    "model": "stratus",
    "hybrid": 0,
    "segm1": 3,
    "Quantity": 99648,
    "Price": 20770,
    "wheel_base": 108,
    "length": 191.2,
    "width": 70.6,
    "weight": 3182,
    "disp": 2.4,
    "hp": 150,
    "mpg_city": 24,
    "mpg_highway": 28,
    "": "",
    "__1": ""
  },
  {
    "car": 1,
    "year": 2005,
    "firm_id": 18,
    "firm_name": "FORD",
    "division": "ford",
    "model": "FIVE HUNDRED",
    "hybrid": 0,
    "segm1": 4,
    "Quantity": 107932,
    "Price": 22795,
    "wheel_base": 112.9,
    "length": 200.7,
    "width": 73.7,
    "weight": 3643,
    "disp": 3,
    "hp": 203,
    "mpg_city": 21,
    "mpg_highway": 29,
    "": "",
    "__1": ""
  },
  {
    "car": 1,
    "year": 2005,
    "firm_id": 18,
    "firm_name": "FORD",
    "division": "ford",
    "model": "crown victoria",
    "hybrid": 0,
    "segm1": 3,
    "Quantity": 63939,
    "Price": 24810,
    "wheel_base": 114.7,
    "length": 212,
    "width": 78.2,
    "weight": 4101,
    "disp": 4.6,
    "hp": 224,
    "mpg_city": 18,
    "mpg_highway": 25,
    "": "",
    "__1": ""
  },
  {
    "car": 1,
    "year": 2005,
    "firm_id": 18,
    "firm_name": "FORD",
    "division": "ford",
    "model": "focus",
    "hybrid": 0,
    "segm1": 2,
    "Quantity": 184825,
    "Price": 14235,
    "wheel_base": 103,
    "length": 175.2,
    "width": 66.7,
    "weight": 2697,
    "disp": 2,
    "hp": 136,
    "mpg_city": 26,
    "mpg_highway": 32,
    "": "",
    "__1": ""
  },
  {
    "car": 1,
    "year": 2005,
    "firm_id": 18,
    "firm_name": "FORD",
    "division": "ford",
    "model": "mustang",
    "hybrid": 0,
    "segm1": 1,
    "Quantity": 160975,
    "Price": 19410,
    "wheel_base": 107.1,
    "length": 187.6,
    "width": 73.9,
    "weight": 3351,
    "disp": 4,
    "hp": 210,
    "mpg_city": 19,
    "mpg_highway": 25,
    "": "",
    "__1": ""
  },
  {
    "car": 1,
    "year": 2005,
    "firm_id": 18,
    "firm_name": "FORD",
    "division": "ford",
    "model": "taurus",
    "hybrid": 0,
    "segm1": 3,
    "Quantity": 196919,
    "Price": 21145,
    "wheel_base": 108.5,
    "length": 197.5,
    "width": 73,
    "weight": 3306,
    "disp": 3,
    "hp": 155,
    "mpg_city": 20,
    "mpg_highway": 27,
    "": "",
    "__1": ""
  },
  {
    "car": 1,
    "year": 2005,
    "firm_id": 18,
    "firm_name": "FORD",
    "division": "ford",
    "model": "thunderbird",
    "hybrid": 0,
    "segm1": 5,
    "Quantity": 9548,
    "Price": 38085,
    "wheel_base": 107.2,
    "length": 186.3,
    "width": 72,
    "weight": 3780,
    "disp": 3.9,
    "hp": 280,
    "mpg_city": 18,
    "mpg_highway": 24,
    "": "",
    "__1": ""
  },
  {
    "car": 1,
    "year": 2005,
    "firm_id": 3,
    "firm_name": "HONDA",
    "division": "honda",
    "model": "accord",
    "hybrid": 0,
    "segm1": 2,
    "Quantity": 352467,
    "Price": 20290,
    "wheel_base": 105.1,
    "length": 187.6,
    "width": 71.3,
    "weight": 2994,
    "disp": 2.4,
    "hp": 160,
    "mpg_city": 26,
    "mpg_highway": 34,
    "": "",
    "__1": ""
  },
  {
    "car": 1,
    "year": 2005,
    "firm_id": 3,
    "firm_name": "HONDA",
    "division": "honda",
    "model": "accord hybrid",
    "hybrid": 1,
    "segm1": 2,
    "Quantity": 16826,
    "Price": 30505,
    "wheel_base": 107.9,
    "length": 189.5,
    "width": 71.5,
    "weight": 3501,
    "disp": 3,
    "hp": 255,
    "mpg_city": 26,
    "mpg_highway": 34,
    "": "",
    "__1": ""
  },
  {
    "car": 1,
    "year": 2005,
    "firm_id": 3,
    "firm_name": "HONDA",
    "division": "honda",
    "model": "civic",
    "hybrid": 0,
    "segm1": 1,
    "Quantity": 282551,
    "Price": 14375,
    "wheel_base": 103.1,
    "length": 175.4,
    "width": 66.7,
    "weight": 2500,
    "disp": 1.7,
    "hp": 117,
    "mpg_city": 36,
    "mpg_highway": 34,
    "": "",
    "__1": ""
  },
  {
    "car": 1,
    "year": 2005,
    "firm_id": 3,
    "firm_name": "HONDA",
    "division": "honda",
    "model": "civic hybrid",
    "hybrid": 1,
    "segm1": 1,
    "Quantity": 25864,
    "Price": 20165,
    "wheel_base": 103.1,
    "length": 175.4,
    "width": 66.7,
    "weight": 2500,
    "disp": 1.3,
    "hp": 85,
    "mpg_city": 48,
    "mpg_highway": 48,
    "": "",
    "__1": ""
  },
  {
    "car": 1,
    "year": 2005,
    "firm_id": 3,
    "firm_name": "HONDA",
    "division": "honda",
    "model": "insight",
    "hybrid": 1,
    "segm1": 1,
    "Quantity": 666,
    "Price": 19695,
    "wheel_base": 94.5,
    "length": 155.1,
    "width": 66.7,
    "weight": 1850,
    "disp": 1,
    "hp": 67,
    "mpg_city": 61,
    "mpg_highway": 56,
    "": "",
    "__1": ""
  },
  {
    "car": 1,
    "year": 2005,
    "firm_id": 21,
    "firm_name": "HYUNDAI",
    "division": "hyundai",
    "model": "accent",
    "hybrid": 0,
    "segm1": 1,
    "Quantity": 41012,
    "Price": 10544,
    "wheel_base": 96.1,
    "length": 166.7,
    "width": 65.7,
    "weight": 2280,
    "disp": 1.6,
    "hp": 104,
    "mpg_city": 29,
    "mpg_highway": 35,
    "": "",
    "__1": ""
  },
  {
    "car": 1,
    "year": 2005,
    "firm_id": 21,
    "firm_name": "HYUNDAI",
    "division": "hyundai",
    "model": "elantra",
    "hybrid": 0,
    "segm1": 2,
    "Quantity": 116336,
    "Price": 13844,
    "wheel_base": 102.7,
    "length": 178.1,
    "width": 67.9,
    "weight": 2635,
    "disp": 2,
    "hp": 138,
    "mpg_city": 27,
    "mpg_highway": 32,
    "": "",
    "__1": ""
  },
  {
    "car": 1,
    "year": 2005,
    "firm_id": 21,
    "firm_name": "HYUNDAI",
    "division": "hyundai",
    "model": "sonata",
    "hybrid": 0,
    "segm1": 2,
    "Quantity": 130365,
    "Price": 16594,
    "wheel_base": 106.3,
    "length": 186.9,
    "width": 71.7,
    "weight": 3181,
    "disp": 2.4,
    "hp": 138,
    "mpg_city": 22,
    "mpg_highway": 30,
    "": "",
    "__1": ""
  },
  {
    "car": 1,
    "year": 2005,
    "firm_id": 21,
    "firm_name": "HYUNDAI",
    "division": "hyundai",
    "model": "tiburon",
    "hybrid": 0,
    "segm1": 1,
    "Quantity": 20600,
    "Price": 16999,
    "wheel_base": 99.6,
    "length": 173,
    "width": 69.3,
    "weight": 2940,
    "disp": 2,
    "hp": 138,
    "mpg_city": 24,
    "mpg_highway": 30,
    "": "",
    "__1": ""
  },
  {
    "car": 1,
    "year": 2005,
    "firm_id": 21,
    "firm_name": "HYUNDAI",
    "division": "hyundai",
    "model": "xg300",
    "hybrid": 0,
    "segm1": 3,
    "Quantity": 17645,
    "Price": 24994,
    "wheel_base": 108.3,
    "length": 191.9,
    "width": 71.9,
    "weight": 3651,
    "disp": 3.5,
    "hp": 194,
    "mpg_city": 18,
    "mpg_highway": 26,
    "": "",
    "__1": ""
  },
  {
    "car": 1,
    "year": 2005,
    "firm_id": 2,
    "firm_name": "NISSAN",
    "division": "infiniti",
    "model": "g35 m35",
    "hybrid": 0,
    "segm1": 3,
    "Quantity": 68728,
    "Price": 31290,
    "wheel_base": 112.2,
    "length": 186.5,
    "width": 69,
    "weight": 3468,
    "disp": 3.5,
    "hp": 280,
    "mpg_city": 19,
    "mpg_highway": 26,
    "": "",
    "__1": ""
  },
  {
    "car": 1,
    "year": 2005,
    "firm_id": 2,
    "firm_name": "NISSAN",
    "division": "infiniti",
    "model": "q45 m45",
    "hybrid": 0,
    "segm1": 5,
    "Quantity": 1129,
    "Price": 56490,
    "wheel_base": 113,
    "length": 200.8,
    "width": 72.6,
    "weight": 4050,
    "disp": 4.5,
    "hp": 340,
    "mpg_city": 17,
    "mpg_highway": 23,
    "": "",
    "__1": ""
  },
  {
    "car": 1,
    "year": 2005,
    "firm_id": 22,
    "firm_name": "JAGUAR",
    "division": "jaguar",
    "model": "xj8",
    "hybrid": 0,
    "segm1": 5,
    "Quantity": 8304,
    "Price": 61495,
    "wheel_base": 119.4,
    "length": 200.4,
    "width": 83,
    "weight": 3806,
    "disp": 4.2,
    "hp": 294,
    "mpg_city": 18,
    "mpg_highway": 26,
    "": "",
    "__1": ""
  },
  {
    "car": 1,
    "year": 2005,
    "firm_id": 22,
    "firm_name": "JAGUAR",
    "division": "jaguar",
    "model": "XK8",
    "hybrid": 0,
    "segm1": 5,
    "Quantity": 2282,
    "Price": 70495,
    "wheel_base": 102,
    "length": 188,
    "width": 81.7,
    "weight": 3779,
    "disp": 4.2,
    "hp": 294,
    "mpg_city": 18,
    "mpg_highway": 26,
    "": "",
    "__1": ""
  },
  {
    "car": 1,
    "year": 2005,
    "firm_id": 22,
    "firm_name": "JAGUAR",
    "division": "jaguar",
    "model": "S-TYPE",
    "hybrid": 0,
    "segm1": 5,
    "Quantity": 8897,
    "Price": 44895,
    "wheel_base": 114.5,
    "length": 193,
    "width": 81.1,
    "weight": 3777,
    "disp": 3,
    "hp": 235,
    "mpg_city": 18,
    "mpg_highway": 26,
    "": "",
    "__1": ""
  },
  {
    "car": 1,
    "year": 2005,
    "firm_id": 22,
    "firm_name": "JAGUAR",
    "division": "jaguar",
    "model": "X-TYPE",
    "hybrid": 0,
    "segm1": 5,
    "Quantity": 10941,
    "Price": 30995,
    "wheel_base": 106.7,
    "length": 183.9,
    "width": 78.8,
    "weight": 3498,
    "disp": 2.5,
    "hp": 192,
    "mpg_city": 18,
    "mpg_highway": 26,
    "": "",
    "__1": ""
  },
  {
    "car": 1,
    "year": 2005,
    "firm_id": 30,
    "firm_name": "KIA",
    "division": "kia",
    "model": "amanti",
    "hybrid": 0,
    "segm1": 3,
    "Quantity": 18668,
    "Price": 25790,
    "wheel_base": 110.2,
    "length": 196,
    "width": 72.8,
    "weight": 4021,
    "disp": 3.5,
    "hp": 200,
    "mpg_city": 17,
    "mpg_highway": 25,
    "": "",
    "__1": ""
  },
  {
    "car": 1,
    "year": 2005,
    "firm_id": 30,
    "firm_name": "KIA",
    "division": "kia",
    "model": "optima",
    "hybrid": 0,
    "segm1": 3,
    "Quantity": 41349,
    "Price": 16490,
    "wheel_base": 106.3,
    "length": 185.8,
    "width": 71.5,
    "weight": 3281,
    "disp": 2.4,
    "hp": 138,
    "mpg_city": 22,
    "mpg_highway": 30,
    "": "",
    "__1": ""
  },
  {
    "car": 1,
    "year": 2005,
    "firm_id": 30,
    "firm_name": "KIA",
    "division": "kia",
    "model": "rio",
    "hybrid": 0,
    "segm1": 1,
    "Quantity": 30290,
    "Price": 10390,
    "wheel_base": 94.9,
    "length": 166.9,
    "width": 65.9,
    "weight": 2403,
    "disp": 1.6,
    "hp": 104,
    "mpg_city": 25,
    "mpg_highway": 32,
    "": "",
    "__1": ""
  },
  {
    "car": 1,
    "year": 2005,
    "firm_id": 30,
    "firm_name": "KIA",
    "division": "kia",
    "model": "spectra",
    "hybrid": 0,
    "segm1": 2,
    "Quantity": 56088,
    "Price": 13240,
    "wheel_base": 102.8,
    "length": 176.4,
    "width": 68.3,
    "weight": 2701,
    "disp": 2,
    "hp": 138,
    "mpg_city": 24,
    "mpg_highway": 34,
    "": "",
    "__1": ""
  },
  {
    "car": 1,
    "year": 2005,
    "firm_id": 1,
    "firm_name": "TOYOTA",
    "division": "lexus",
    "model": "es300",
    "hybrid": 0,
    "segm1": 5,
    "Quantity": 67577,
    "Price": 32600,
    "wheel_base": 107.1,
    "length": 191.1,
    "width": 71.3,
    "weight": 3472,
    "disp": 3.3,
    "hp": 225,
    "mpg_city": 21,
    "mpg_highway": 29,
    "": "",
    "__1": ""
  },
  {
    "car": 1,
    "year": 2005,
    "firm_id": 1,
    "firm_name": "TOYOTA",
    "division": "lexus",
    "model": "gs300",
    "hybrid": 0,
    "segm1": 5,
    "Quantity": 27807,
    "Price": 39500,
    "wheel_base": 110.2,
    "length": 189.2,
    "width": 70.9,
    "weight": 3649,
    "disp": 3,
    "hp": 220,
    "mpg_city": 18,
    "mpg_highway": 25,
    "": "",
    "__1": ""
  },
  {
    "car": 1,
    "year": 2005,
    "firm_id": 1,
    "firm_name": "TOYOTA",
    "division": "lexus",
    "model": "IS",
    "hybrid": 0,
    "segm1": 5,
    "Quantity": 15789,
    "Price": 29980,
    "wheel_base": 105.1,
    "length": 176.6,
    "width": 67.7,
    "weight": 3255,
    "disp": 3,
    "hp": 215,
    "mpg_city": 18,
    "mpg_highway": 25,
    "": "",
    "__1": ""
  },
  {
    "car": 1,
    "year": 2005,
    "firm_id": 1,
    "firm_name": "TOYOTA",
    "division": "lexus",
    "model": "ls430",
    "hybrid": 0,
    "segm1": 5,
    "Quantity": 26043,
    "Price": 56300,
    "wheel_base": 115.2,
    "length": 197.4,
    "width": 72,
    "weight": 3990,
    "disp": 4.3,
    "hp": 290,
    "mpg_city": 18,
    "mpg_highway": 25,
    "": "",
    "__1": ""
  },
  {
    "car": 1,
    "year": 2005,
    "firm_id": 1,
    "firm_name": "TOYOTA",
    "division": "lexus",
    "model": "SC430",
    "hybrid": 0,
    "segm1": 5,
    "Quantity": 8360,
    "Price": 63800,
    "wheel_base": 103.1,
    "length": 177.8,
    "width": 72,
    "weight": 3840,
    "disp": 4.3,
    "hp": 300,
    "mpg_city": 18,
    "mpg_highway": 23,
    "": "",
    "__1": ""
  },
  {
    "car": 1,
    "year": 2005,
    "firm_id": 18,
    "firm_name": "FORD",
    "division": "lincoln",
    "model": "LS",
    "hybrid": 0,
    "segm1": 5,
    "Quantity": 19109,
    "Price": 32965,
    "wheel_base": 114.5,
    "length": 194.3,
    "width": 73.2,
    "weight": 3681,
    "disp": 3,
    "hp": 232,
    "mpg_city": 20,
    "mpg_highway": 26,
    "": "",
    "__1": ""
  },
  {
    "car": 1,
    "year": 2005,
    "firm_id": 18,
    "firm_name": "FORD",
    "division": "lincoln",
    "model": "town car",
    "hybrid": 0,
    "segm1": 5,
    "Quantity": 47122,
    "Price": 42470,
    "wheel_base": 117.7,
    "length": 216.2,
    "width": 78.2,
    "weight": 4345,
    "disp": 4.6,
    "hp": 239,
    "mpg_city": 18,
    "mpg_highway": 25,
    "": "",
    "__1": ""
  },
  {
    "car": 1,
    "year": 2005,
    "firm_id": 18,
    "firm_name": "FORD",
    "division": "lincoln mercury",
    "model": "grand marquis",
    "hybrid": 0,
    "segm1": 4,
    "Quantity": 64716,
    "Price": 25095,
    "wheel_base": 114.7,
    "length": 212,
    "width": 78.2,
    "weight": 4135,
    "disp": 4.6,
    "hp": 224,
    "mpg_city": 18,
    "mpg_highway": 25,
    "": "",
    "__1": ""
  },
  {
    "car": 1,
    "year": 2005,
    "firm_id": 18,
    "firm_name": "FORD",
    "division": "lincoln mercury",
    "model": "montego",
    "hybrid": 0,
    "segm1": 4,
    "Quantity": 27007,
    "Price": 24995,
    "wheel_base": 112.9,
    "length": 200.9,
    "width": 74.5,
    "weight": 3680,
    "disp": 4,
    "hp": 203,
    "mpg_city": 19,
    "mpg_highway": 26,
    "": "",
    "__1": ""
  },
  {
    "car": 1,
    "year": 2005,
    "firm_id": 18,
    "firm_name": "FORD",
    "division": "lincoln mercury",
    "model": "sable",
    "hybrid": 0,
    "segm1": 3,
    "Quantity": 24149,
    "Price": 21595,
    "wheel_base": 108.5,
    "length": 199.7,
    "width": 73,
    "weight": 3308,
    "disp": 3,
    "hp": 155,
    "mpg_city": 20,
    "mpg_highway": 27,
    "": "",
    "__1": ""
  },
  {
    "car": 1,
    "year": 2005,
    "firm_id": 4,
    "firm_name": "MAZDA",
    "division": "MAZDA",
    "model": "mazda3",
    "hybrid": 0,
    "segm1": 1,
    "Quantity": 97388,
    "Price": 14225,
    "wheel_base": 103.9,
    "length": 178.3,
    "width": 69.1,
    "weight": 2696,
    "disp": 2,
    "hp": 148,
    "mpg_city": 18,
    "mpg_highway": 24,
    "": "",
    "__1": ""
  },
  {
    "car": 1,
    "year": 2005,
    "firm_id": 4,
    "firm_name": "MAZDA",
    "division": "MAZDA",
    "model": "mazda6",
    "hybrid": 0,
    "segm1": 2,
    "Quantity": 71447,
    "Price": 19540,
    "wheel_base": 105.3,
    "length": 186.8,
    "width": 70.1,
    "weight": 3102,
    "disp": 2.3,
    "hp": 160,
    "mpg_city": 18,
    "mpg_highway": 24,
    "": "",
    "__1": ""
  },
  {
    "car": 1,
    "year": 2005,
    "firm_id": 4,
    "firm_name": "MAZDA",
    "division": "MAZDA",
    "model": "mx-5 miata",
    "hybrid": 0,
    "segm1": 1,
    "Quantity": 9801,
    "Price": 22643,
    "wheel_base": 89.2,
    "length": 155.3,
    "width": 66,
    "weight": 2447,
    "disp": 1.8,
    "hp": 142,
    "mpg_city": 23,
    "mpg_highway": 28,
    "": "",
    "__1": ""
  },
  {
    "car": 1,
    "year": 2005,
    "firm_id": 9,
    "firm_name": "MERCEDEZ",
    "division": "MERCEDEZ",
    "model": "C230",
    "hybrid": 0,
    "segm1": 3,
    "Quantity": 60658,
    "Price": 26570,
    "wheel_base": 106.9,
    "length": 178.4,
    "width": 68,
    "weight": 3250,
    "disp": 1.8,
    "hp": 189,
    "mpg_city": 24,
    "mpg_highway": 32,
    "": "",
    "__1": ""
  },
  {
    "car": 1,
    "year": 2005,
    "firm_id": 9,
    "firm_name": "MERCEDEZ",
    "division": "MERCEDEZ",
    "model": "clk320",
    "hybrid": 0,
    "segm1": 5,
    "Quantity": 18227,
    "Price": 45970,
    "wheel_base": 106.9,
    "length": 182.6,
    "width": 68.5,
    "weight": 3515,
    "disp": 3.2,
    "hp": 215,
    "mpg_city": 20,
    "mpg_highway": 28,
    "": "",
    "__1": ""
  },
  {
    "car": 1,
    "year": 2005,
    "firm_id": 9,
    "firm_name": "MERCEDEZ",
    "division": "MERCEDEZ",
    "model": "E320",
    "hybrid": 0,
    "segm1": 5,
    "Quantity": 50383,
    "Price": 49220,
    "wheel_base": 112.4,
    "length": 189.7,
    "width": 71.3,
    "weight": 3835,
    "disp": 3.2,
    "hp": 201,
    "mpg_city": 20,
    "mpg_highway": 28,
    "": "",
    "__1": ""
  },
  {
    "car": 1,
    "year": 2005,
    "firm_id": 9,
    "firm_name": "MERCEDEZ",
    "division": "MERCEDEZ",
    "model": "S430",
    "hybrid": 0,
    "segm1": 5,
    "Quantity": 16036,
    "Price": 76030,
    "wheel_base": 121.5,
    "length": 203.1,
    "width": 73.1,
    "weight": 4160,
    "disp": 4.3,
    "hp": 275,
    "mpg_city": 17,
    "mpg_highway": 26,
    "": "",
    "__1": ""
  },
  {
    "car": 1,
    "year": 2005,
    "firm_id": 9,
    "firm_name": "MERCEDEZ",
    "division": "MERCEDEZ",
    "model": "SL coupe",
    "hybrid": 0,
    "segm1": 5,
    "Quantity": 10080,
    "Price": 90620,
    "wheel_base": 100.8,
    "length": 178.5,
    "width": 71.5,
    "weight": 4065,
    "disp": 5,
    "hp": 302,
    "mpg_city": 16,
    "mpg_highway": 23,
    "": "",
    "__1": ""
  },
  {
    "car": 1,
    "year": 2005,
    "firm_id": 9,
    "firm_name": "MERCEDEZ",
    "division": "MERCEDEZ",
    "model": "slk",
    "hybrid": 0,
    "segm1": 5,
    "Quantity": 11278,
    "Price": 46220,
    "wheel_base": 95.7,
    "length": 160.7,
    "width": 70.4,
    "weight": 3231,
    "disp": 3.5,
    "hp": 268,
    "mpg_city": 19,
    "mpg_highway": 25,
    "": "",
    "__1": ""
  },
  {
    "car": 1,
    "year": 2005,
    "firm_id": 45,
    "firm_name": "MINI",
    "division": "mini",
    "model": "mini cooper",
    "hybrid": 0,
    "segm1": 1,
    "Quantity": 40820,
    "Price": 16999,
    "wheel_base": 97.1,
    "length": 143.1,
    "width": 66.5,
    "weight": 2700,
    "disp": 1.6,
    "hp": 115,
    "mpg_city": 28,
    "mpg_highway": 37,
    "": "",
    "__1": ""
  },
  {
    "car": 1,
    "year": 2005,
    "firm_id": 10,
    "firm_name": "MITSUBIS",
    "division": "mitsubishi",
    "model": "eclipse",
    "hybrid": 0,
    "segm1": 2,
    "Quantity": 21193,
    "Price": 20044,
    "wheel_base": 100.8,
    "length": 176.8,
    "width": 68.9,
    "weight": 2910,
    "disp": 2.4,
    "hp": 142,
    "mpg_city": 23,
    "mpg_highway": 31,
    "": "",
    "__1": ""
  },
  {
    "car": 1,
    "year": 2005,
    "firm_id": 10,
    "firm_name": "MITSUBIS",
    "division": "mitsubishi",
    "model": "galant",
    "hybrid": 0,
    "segm1": 2,
    "Quantity": 33976,
    "Price": 19574,
    "wheel_base": 108.3,
    "length": 190.6,
    "width": 72.4,
    "weight": 3351,
    "disp": 2.4,
    "hp": 160,
    "mpg_city": 23,
    "mpg_highway": 30,
    "": "",
    "__1": ""
  },
  {
    "car": 1,
    "year": 2005,
    "firm_id": 10,
    "firm_name": "MITSUBIS",
    "division": "mitsubishi",
    "model": "lancer",
    "hybrid": 0,
    "segm1": 1,
    "Quantity": 27849,
    "Price": 14574,
    "wheel_base": 102.4,
    "length": 180.5,
    "width": 66.8,
    "weight": 2656,
    "disp": 2,
    "hp": 120,
    "mpg_city": 27,
    "mpg_highway": 31,
    "": "",
    "__1": ""
  },
  {
    "car": 1,
    "year": 2005,
    "firm_id": 2,
    "firm_name": "NISSAN",
    "division": "NISSAN",
    "model": "350z",
    "hybrid": 0,
    "segm1": 1,
    "Quantity": 27278,
    "Price": 27060,
    "wheel_base": 104.3,
    "length": 169.4,
    "width": 71.5,
    "weight": 3188,
    "disp": 3.5,
    "hp": 287,
    "mpg_city": 20,
    "mpg_highway": 26,
    "": "",
    "__1": ""
  },
  {
    "car": 1,
    "year": 2005,
    "firm_id": 2,
    "firm_name": "NISSAN",
    "division": "NISSAN",
    "model": "altima",
    "hybrid": 0,
    "segm1": 3,
    "Quantity": 255371,
    "Price": 17760,
    "wheel_base": 110.2,
    "length": 192.3,
    "width": 70.4,
    "weight": 3001,
    "disp": 2.5,
    "hp": 175,
    "mpg_city": 24,
    "mpg_highway": 29,
    "": "",
    "__1": ""
  },
  {
    "car": 1,
    "year": 2005,
    "firm_id": 2,
    "firm_name": "NISSAN",
    "division": "NISSAN",
    "model": "maxima",
    "hybrid": 0,
    "segm1": 3,
    "Quantity": 75425,
    "Price": 27660,
    "wheel_base": 111.2,
    "length": 193.5,
    "width": 71.7,
    "weight": 3432,
    "disp": 3.5,
    "hp": 265,
    "mpg_city": 20,
    "mpg_highway": 29,
    "": "",
    "__1": ""
  },
  {
    "car": 1,
    "year": 2005,
    "firm_id": 2,
    "firm_name": "NISSAN",
    "division": "NISSAN",
    "model": "sentra",
    "hybrid": 0,
    "segm1": 2,
    "Quantity": 119489,
    "Price": 13060,
    "wheel_base": 99.8,
    "length": 177.5,
    "width": 67.3,
    "weight": 2519,
    "disp": 1.8,
    "hp": 126,
    "mpg_city": 28,
    "mpg_highway": 34,
    "": "",
    "__1": ""
  },
  {
    "car": 1,
    "year": 2005,
    "firm_id": 19,
    "firm_name": "GM",
    "division": "pontiac",
    "model": "bonneville",
    "hybrid": 0,
    "segm1": 4,
    "Quantity": 10037,
    "Price": 28500,
    "wheel_base": 112.2,
    "length": 202.6,
    "width": 74.2,
    "weight": 3590,
    "disp": 3.8,
    "hp": 205,
    "mpg_city": 20,
    "mpg_highway": 29,
    "": "",
    "__1": ""
  },
  {
    "car": 1,
    "year": 2005,
    "firm_id": 19,
    "firm_name": "GM",
    "division": "pontiac",
    "model": "g6",
    "hybrid": 0,
    "segm1": 3,
    "Quantity": 124844,
    "Price": 21300,
    "wheel_base": 112.3,
    "length": 189,
    "width": 70.6,
    "weight": 3380,
    "disp": 3.5,
    "hp": 200,
    "mpg_city": 22,
    "mpg_highway": 32,
    "": "",
    "__1": ""
  },
  {
    "car": 1,
    "year": 2005,
    "firm_id": 19,
    "firm_name": "GM",
    "division": "pontiac",
    "model": "grand am",
    "hybrid": 0,
    "segm1": 2,
    "Quantity": 31613,
    "Price": 22990,
    "wheel_base": 107.2,
    "length": 186.3,
    "width": 70.4,
    "weight": 3116,
    "disp": 3.4,
    "hp": 175,
    "mpg_city": 25,
    "mpg_highway": 34,
    "": "",
    "__1": ""
  },
  {
    "car": 1,
    "year": 2005,
    "firm_id": 19,
    "firm_name": "GM",
    "division": "pontiac",
    "model": "grand prix",
    "hybrid": 0,
    "segm1": 3,
    "Quantity": 122398,
    "Price": 23560,
    "wheel_base": 110.5,
    "length": 198.3,
    "width": 73.8,
    "weight": 3477,
    "disp": 3.8,
    "hp": 200,
    "mpg_city": 20,
    "mpg_highway": 28,
    "": "",
    "__1": ""
  },
  {
    "car": 1,
    "year": 2005,
    "firm_id": 19,
    "firm_name": "GM",
    "division": "pontiac",
    "model": "sunfire",
    "hybrid": 0,
    "segm1": 1,
    "Quantity": 25114,
    "Price": 15650,
    "wheel_base": 104.1,
    "length": 182,
    "width": 68.4,
    "weight": 2771,
    "disp": 2.2,
    "hp": 140,
    "mpg_city": 26,
    "mpg_highway": 34,
    "": "",
    "__1": ""
  },
  {
    "car": 1,
    "year": 2005,
    "firm_id": 19,
    "firm_name": "GM",
    "division": "pontiac",
    "model": "vibe",
    "hybrid": 0,
    "segm1": 1,
    "Quantity": 64271,
    "Price": 17560,
    "wheel_base": 102.4,
    "length": 171.9,
    "width": 69.9,
    "weight": 2701,
    "disp": 1.8,
    "hp": 130,
    "mpg_city": 30,
    "mpg_highway": 34,
    "": "",
    "__1": ""
  },
  {
    "car": 1,
    "year": 2005,
    "firm_id": 12,
    "firm_name": "PORSCHE",
    "division": "porsche",
    "model": "911 carrera",
    "hybrid": 0,
    "segm1": 5,
    "Quantity": 8963,
    "Price": 70095,
    "wheel_base": 92.6,
    "length": 175.6,
    "width": 71.2,
    "weight": 3075,
    "disp": 3.6,
    "hp": 315,
    "mpg_city": 20,
    "mpg_highway": 29,
    "": "",
    "__1": ""
  },
  {
    "car": 1,
    "year": 2005,
    "firm_id": 12,
    "firm_name": "PORSCHE",
    "division": "porsche",
    "model": "boxster",
    "hybrid": 0,
    "segm1": 5,
    "Quantity": 7879,
    "Price": 44545,
    "wheel_base": 95.2,
    "length": 170.4,
    "width": 70.9,
    "weight": 2855,
    "disp": 2.7,
    "hp": 240,
    "mpg_city": 20,
    "mpg_highway": 29,
    "": "",
    "__1": ""
  },
  {
    "car": 1,
    "year": 2005,
    "firm_id": 11,
    "firm_name": "SAAB",
    "division": "saab",
    "model": 92,
    "hybrid": 0,
    "segm1": 3,
    "Quantity": 5940,
    "Price": 23685,
    "wheel_base": 99.4,
    "length": 173.8,
    "width": 68.1,
    "weight": 3070,
    "disp": 2.5,
    "hp": 165,
    "mpg_city": 21,
    "mpg_highway": 28,
    "": "",
    "__1": ""
  },
  {
    "car": 1,
    "year": 2005,
    "firm_id": 11,
    "firm_name": "SAAB",
    "division": "saab",
    "model": 93,
    "hybrid": 0,
    "segm1": 3,
    "Quantity": 24108,
    "Price": 27570,
    "wheel_base": 105.3,
    "length": 182.5,
    "width": 69,
    "weight": 3175,
    "disp": 2,
    "hp": 175,
    "mpg_city": 21,
    "mpg_highway": 28,
    "": "",
    "__1": ""
  },
  {
    "car": 1,
    "year": 2005,
    "firm_id": 11,
    "firm_name": "SAAB",
    "division": "saab",
    "model": 95,
    "hybrid": 0,
    "segm1": 5,
    "Quantity": 6023,
    "Price": 36970,
    "wheel_base": 106.4,
    "length": 190,
    "width": 70.5,
    "weight": 3580,
    "disp": 2.3,
    "hp": 220,
    "mpg_city": 20,
    "mpg_highway": 30,
    "": "",
    "__1": ""
  },
  {
    "car": 1,
    "year": 2005,
    "firm_id": 19,
    "firm_name": "GM",
    "division": "saturn",
    "model": "ION",
    "hybrid": 0,
    "segm1": 1,
    "Quantity": 100891,
    "Price": 11995,
    "wheel_base": 103.2,
    "length": 184.5,
    "width": 67.2,
    "weight": 2692,
    "disp": 2.2,
    "hp": 140,
    "mpg_city": 26,
    "mpg_highway": 29,
    "": "",
    "__1": ""
  },
  {
    "car": 1,
    "year": 2005,
    "firm_id": 19,
    "firm_name": "GM",
    "division": "saturn",
    "model": "LS",
    "hybrid": 0,
    "segm1": 2,
    "Quantity": 5036,
    "Price": 21995,
    "wheel_base": 106.5,
    "length": 190.4,
    "width": 68.5,
    "weight": 3237,
    "disp": 3,
    "hp": 182,
    "mpg_city": 21,
    "mpg_highway": 27,
    "": "",
    "__1": ""
  },
  {
    "car": 1,
    "year": 2005,
    "firm_id": 5,
    "firm_name": "SUBARU",
    "division": "SUBARU",
    "model": "impreza",
    "hybrid": 0,
    "segm1": 1,
    "Quantity": 33637,
    "Price": 18670,
    "wheel_base": 99.4,
    "length": 173.8,
    "width": 68.5,
    "weight": 2972,
    "disp": 2.5,
    "hp": 165,
    "mpg_city": 23,
    "mpg_highway": 26,
    "": "",
    "__1": ""
  },
  {
    "car": 1,
    "year": 2005,
    "firm_id": 5,
    "firm_name": "SUBARU",
    "division": "SUBARU",
    "model": "legacy",
    "hybrid": 0,
    "segm1": 2,
    "Quantity": 87788,
    "Price": 21870,
    "wheel_base": 105.1,
    "length": 186.2,
    "width": 68.1,
    "weight": 3200,
    "disp": 2.5,
    "hp": 168,
    "mpg_city": 23,
    "mpg_highway": 25,
    "": "",
    "__1": ""
  },
  {
    "car": 1,
    "year": 2005,
    "firm_id": 31,
    "firm_name": "SUZUKI",
    "division": "suzuki",
    "model": "aerio",
    "hybrid": 0,
    "segm1": 1,
    "Quantity": 7967,
    "Price": 13994,
    "wheel_base": 97.6,
    "length": 171.3,
    "width": 67.7,
    "weight": 2661,
    "disp": 2.3,
    "hp": 155,
    "mpg_city": 25,
    "mpg_highway": 31,
    "": "",
    "__1": ""
  },
  {
    "car": 1,
    "year": 2005,
    "firm_id": 31,
    "firm_name": "SUZUKI",
    "division": "Suzuki",
    "model": "forenza",
    "hybrid": 0,
    "segm1": 2,
    "Quantity": 41394,
    "Price": 13994,
    "wheel_base": 102.4,
    "length": 177.2,
    "width": 67.9,
    "weight": 2701,
    "disp": 2,
    "hp": 126,
    "mpg_city": 22,
    "mpg_highway": 30,
    "": "",
    "__1": ""
  },
  {
    "car": 1,
    "year": 2005,
    "firm_id": 31,
    "firm_name": "SUZUKI",
    "division": "Suzuki",
    "model": "verona",
    "hybrid": 0,
    "segm1": 3,
    "Quantity": 8411,
    "Price": 17994,
    "wheel_base": 106.3,
    "length": 187.6,
    "width": 71.5,
    "weight": 3380,
    "disp": 2.5,
    "hp": 155,
    "mpg_city": 20,
    "mpg_highway": 28,
    "": "",
    "__1": ""
  },
  {
    "car": 1,
    "year": 2005,
    "firm_id": 59,
    "firm_name": "TOYOTA",
    "division": "TOYOTA",
    "model": "tc",
    "hybrid": 0,
    "segm1": 1,
    "Quantity": 74415,
    "Price": 16465,
    "wheel_base": 106.3,
    "length": 174,
    "width": 69.1,
    "weight": 2905,
    "disp": 2.4,
    "hp": 160,
    "mpg_city": 22,
    "mpg_highway": 29,
    "": "",
    "__1": ""
  },
  {
    "car": 1,
    "year": 2005,
    "firm_id": 59,
    "firm_name": "TOYOTA",
    "division": "TOYOTA",
    "model": "scion xa",
    "hybrid": 0,
    "segm1": 1,
    "Quantity": 28033,
    "Price": 12995,
    "wheel_base": 93.3,
    "length": 154.1,
    "width": 66.7,
    "weight": 2340,
    "disp": 1.5,
    "hp": 108,
    "mpg_city": 32,
    "mpg_highway": 38,
    "": "",
    "__1": ""
  },
  {
    "car": 1,
    "year": 2005,
    "firm_id": 1,
    "firm_name": "TOYOTA",
    "division": "TOYOTA",
    "model": "avalon",
    "hybrid": 0,
    "segm1": 4,
    "Quantity": 95318,
    "Price": 31340,
    "wheel_base": 111,
    "length": 197.2,
    "width": 72.8,
    "weight": 3560,
    "disp": 3.5,
    "hp": 280,
    "mpg_city": 21,
    "mpg_highway": 29,
    "": "",
    "__1": ""
  },
  {
    "car": 1,
    "year": 2005,
    "firm_id": 1,
    "firm_name": "TOYOTA",
    "division": "TOYOTA",
    "model": "camry",
    "hybrid": 0,
    "segm1": 3,
    "Quantity": 431703,
    "Price": 18585,
    "wheel_base": 107.1,
    "length": 189.2,
    "width": 70.1,
    "weight": 3086,
    "disp": 2.4,
    "hp": 157,
    "mpg_city": 24,
    "mpg_highway": 32,
    "": "",
    "__1": ""
  },
  {
    "car": 1,
    "year": 2005,
    "firm_id": 1,
    "firm_name": "TOYOTA",
    "division": "TOYOTA",
    "model": "celica",
    "hybrid": 0,
    "segm1": 1,
    "Quantity": 3113,
    "Price": 18210,
    "wheel_base": 102.4,
    "length": 170.5,
    "width": 68.3,
    "weight": 2425,
    "disp": 1.8,
    "hp": 140,
    "mpg_city": 29,
    "mpg_highway": 36,
    "": "",
    "__1": ""
  },
  {
    "car": 1,
    "year": 2005,
    "firm_id": 1,
    "firm_name": "TOYOTA",
    "division": "TOYOTA",
    "model": "corolla",
    "hybrid": 0,
    "segm1": 1,
    "Quantity": 231848,
    "Price": 14220,
    "wheel_base": 102.4,
    "length": 178.3,
    "width": 66.9,
    "weight": 2502,
    "disp": 1.8,
    "hp": 130,
    "mpg_city": 32,
    "mpg_highway": 38,
    "": "",
    "__1": ""
  },
  {
    "car": 1,
    "year": 2005,
    "firm_id": 1,
    "firm_name": "TOYOTA",
    "division": "TOYOTA",
    "model": "matrix",
    "hybrid": 0,
    "segm1": 1,
    "Quantity": 109442,
    "Price": 15300,
    "wheel_base": 102.4,
    "length": 171.3,
    "width": 69.9,
    "weight": 2679,
    "disp": 1.8,
    "hp": 130,
    "mpg_city": 28,
    "mpg_highway": 33,
    "": "",
    "__1": ""
  },
  {
    "car": 1,
    "year": 2005,
    "firm_id": 1,
    "firm_name": "TOYOTA",
    "division": "toyota",
    "model": "prius",
    "hybrid": 1,
    "segm1": 1,
    "Quantity": 107897,
    "Price": 21415,
    "wheel_base": 106.3,
    "length": 175,
    "width": 67.9,
    "weight": 2890,
    "disp": 1.5,
    "hp": 76,
    "mpg_city": 60,
    "mpg_highway": 51,
    "": "",
    "__1": ""
  },
  {
    "car": 1,
    "year": 2005,
    "firm_id": 7,
    "firm_name": "VOLKS",
    "division": "volkswagen",
    "model": "golf",
    "hybrid": 0,
    "segm1": 1,
    "Quantity": 15690,
    "Price": 16405,
    "wheel_base": 98.9,
    "length": 164.9,
    "width": 68.3,
    "weight": 2771,
    "disp": 2,
    "hp": 115,
    "mpg_city": 24,
    "mpg_highway": 30,
    "": "",
    "__1": ""
  },
  {
    "car": 1,
    "year": 2005,
    "firm_id": 7,
    "firm_name": "VOLKS",
    "division": "volkswagen",
    "model": "jetta",
    "hybrid": 0,
    "segm1": 2,
    "Quantity": 104063,
    "Price": 18255,
    "wheel_base": 98.9,
    "length": 172.3,
    "width": 68.3,
    "weight": 2934,
    "disp": 2,
    "hp": 115,
    "mpg_city": 24,
    "mpg_highway": 31,
    "": "",
    "__1": ""
  },
  {
    "car": 1,
    "year": 2005,
    "firm_id": 7,
    "firm_name": "VOLKS",
    "division": "volkswagen",
    "model": "new beetle",
    "hybrid": 0,
    "segm1": 1,
    "Quantity": 36339,
    "Price": 17145,
    "wheel_base": 98.7,
    "length": 161.1,
    "width": 67.9,
    "weight": 2743,
    "disp": 2,
    "hp": 115,
    "mpg_city": 25,
    "mpg_highway": 30,
    "": "",
    "__1": ""
  },
  {
    "car": 1,
    "year": 2005,
    "firm_id": 7,
    "firm_name": "VOLKS",
    "division": "volkswagen",
    "model": "passat",
    "hybrid": 0,
    "segm1": 3,
    "Quantity": 49233,
    "Price": 24955,
    "wheel_base": 106.4,
    "length": 185.2,
    "width": 68.7,
    "weight": 3422,
    "disp": 1.8,
    "hp": 170,
    "mpg_city": 21,
    "mpg_highway": 30,
    "": "",
    "__1": ""
  },
  {
    "car": 1,
    "year": 2005,
    "firm_id": 6,
    "firm_name": "VOLVO",
    "division": "volvo",
    "model": "S40",
    "hybrid": 0,
    "segm1": 3,
    "Quantity": 24241,
    "Price": 23945,
    "wheel_base": 103.9,
    "length": 175.9,
    "width": 69.7,
    "weight": 3084,
    "disp": 2.4,
    "hp": 168,
    "mpg_city": 20,
    "mpg_highway": 27,
    "": "",
    "__1": ""
  },
  {
    "car": 1,
    "year": 2005,
    "firm_id": 6,
    "firm_name": "VOLVO",
    "division": "volvo",
    "model": "s60",
    "hybrid": 0,
    "segm1": 3,
    "Quantity": 24695,
    "Price": 27920,
    "wheel_base": 107,
    "length": 180.2,
    "width": 71,
    "weight": 3662,
    "disp": 2.4,
    "hp": 168,
    "mpg_city": 19,
    "mpg_highway": 26,
    "": "",
    "__1": ""
  },
  {
    "car": 1,
    "year": 2005,
    "firm_id": 6,
    "firm_name": "VOLVO",
    "division": "volvo",
    "model": "v70 c70 s70",
    "hybrid": 0,
    "segm1": 4,
    "Quantity": 22823,
    "Price": 29445,
    "wheel_base": 108.5,
    "length": 185.4,
    "width": 71,
    "weight": 3448,
    "disp": 2.4,
    "hp": 168,
    "mpg_city": 19,
    "mpg_highway": 26,
    "": "",
    "__1": ""
  },
  {
    "car": 1,
    "year": 2005,
    "firm_id": 6,
    "firm_name": "VOLVO",
    "division": "volvo",
    "model": "s80 v80",
    "hybrid": 0,
    "segm1": 5,
    "Quantity": 10181,
    "Price": 36585,
    "wheel_base": 109.9,
    "length": 189.8,
    "width": 72.1,
    "weight": 3576,
    "disp": 2.5,
    "hp": 208,
    "mpg_city": 19,
    "mpg_highway": 26,
    "": "",
    "__1": ""
  }
]
